{
  "category": {
    "id": "64c26fb6b617635c9f793728",
    "description": "",
    "images": [
      {
        "url": "https://wolt-menu-images-cdn.wolt.com/menu-images/61c181c22f677c6771072dc3/08875d68-352b-11ee-a912-6a80df92d869_0ab3958e_2fae_11ee_893b_125a7368bcb8___________________.jpg",
        "blurhash": "jgW:HBhkXKJrOVKBpBlG;;KHcPmS"
      }
    ],
    "name": "საკვები დანამატები",
    "slug": "menucategory-681"
  },
  "categories": [],
  "items": [],
  "options": [],
  "variant_groups": [],
  "metadata": {
    "next_page_token": null,
    "page": 1
  }
}