{
  "category": {
    "id": "67d96e659cb1a746777dc759",
    "description": "",
    "images": [
      {
        "url": "https://wolt-menu-images-cdn.wolt.com/menu-images/67b44faf1c3cc1037b71ca49/f1d00040-03f8-11f0-a59b-2a81327b6fdf_____________2__1_.jpg",
        "blurhash": "j7Vv7PGG;;CpTttTPtGGqXCpgPtS"
      }
    ],
    "name": "ნიუ ნორდიკი",
    "slug": "menucategory-206"
  },
  "categories": [
    {
      "id": "67d96e659cb1a746777dc759",
      "item_ids": [
        "67b85f8047ee3d81c17bf1a8",
        "67b85f8047ee3d81c17bf1a7",
        "67b85f8047ee3d81c17bf1a9",
        "67b85f8047ee3d81c17bf1ab",
        "67b85f8047ee3d81c17bf1b2",
        "67b85f8047ee3d81c17bf1ae",
        "67b85f8047ee3d81c17bf1aa",
        "67b85f8047ee3d81c17bf1ac",
        "67b85f8047ee3d81c17bf1ad",
        "67b85f8047ee3d81c17bf1af",
        "67b85f8047ee3d81c17bf1b0"
      ]
    }
  ],
  "items": [
    {
      "id": "67b85f8047ee3d81c17bf1a8",
      "advertising_info": null,
      "alcohol_permille": 0,
      "allowed_delivery_methods": [
        "homedelivery",
        "eatin",
        "takeaway"
      ],
      "available_times": [
        {
          "days": [
            1,
            2,
            3,
            4,
            5,
            6,
            7
          ],
          "start_time": 0,
          "end_time": 86400000
        }
      ],
      "barcode_gtin": null,
      "caffeine_info": null,
      "can_be_promoted": {
        "basket": true,
        "venue": true,
        "credits": true
      },
      "checksum": "e4514ca1dee5d6fa474d24a1f436f775",
      "description": "",
      "deposit": null,
      "dietary_preferences": [],
      "disabled_info": null,
      "fulfillment_lead_time": null,
      "has_extra_info": false,
      "images": [
        {
          "url": "https://wolt-menu-images-cdn.wolt.com/menu-images/670399a6a6d89a977ae64330/033a114a-f044-11ef-a542-c240d485f0e4_1cad548ea4.jpg",
          "blurhash": "j7WeDFGW;;h4;;ll8zll00TtXKcP"
        }
      ],
      "is_cutlery": false,
      "is_no_contact_delivery_allowed": true,
      "is_wolt_plus_only": false,
      "lowest_price": null,
      "lowest_price_v2": null,
      "max_quantity_per_purchase": null,
      "min_quantity_per_purchase": null,
      "name": "NEW NORDIC ნიუ ნორდიკი მულტივიტამინები მამაკაცებისთვის ტაბ N30",
      "options": [],
      "original_price": null,
      "price": 7823,
      "purchasable_balance": 4,
      "restrictions": [],
      "return_policy": null,
      "sell_by_weight_config": null,
      "should_display_purchasable_balance": false,
      "tags": [],
      "unit_info": null,
      "unit_price": null,
      "variant": null
    },
    {
      "id": "67b85f8047ee3d81c17bf1a7",
      "advertising_info": null,
      "alcohol_permille": 0,
      "allowed_delivery_methods": [
        "homedelivery",
        "eatin",
        "takeaway"
      ],
      "available_times": [
        {
          "days": [
            1,
            2,
            3,
            4,
            5,
            6,
            7
          ],
          "start_time": 0,
          "end_time": 86400000
        }
      ],
      "barcode_gtin": null,
      "caffeine_info": null,
      "can_be_promoted": {
        "basket": true,
        "venue": true,
        "credits": true
      },
      "checksum": "f85c073ecc7b86d157aadeea753ba052",
      "description": "",
      "deposit": null,
      "dietary_preferences": [],
      "disabled_info": null,
      "fulfillment_lead_time": null,
      "has_extra_info": false,
      "images": [
        {
          "url": "https://wolt-menu-images-cdn.wolt.com/menu-images/670399a6a6d89a977ae64330/06e272c4-f044-11ef-9503-de676fc26248_49288c7089.jpg",
          "blurhash": "j7WuPKGD;;h4;IlDcQll00TsXKd4"
        }
      ],
      "is_cutlery": false,
      "is_no_contact_delivery_allowed": true,
      "is_wolt_plus_only": false,
      "lowest_price": null,
      "lowest_price_v2": null,
      "max_quantity_per_purchase": null,
      "min_quantity_per_purchase": null,
      "name": "NEW NORDIC ნიუ ნორდიკი მულტივიტამინები ქალებისთვის ჯანმრთელობა და სილამაზე ტაბ N30",
      "options": [],
      "original_price": null,
      "price": 8523,
      "purchasable_balance": 2,
      "restrictions": [],
      "return_policy": null,
      "sell_by_weight_config": null,
      "should_display_purchasable_balance": false,
      "tags": [],
      "unit_info": null,
      "unit_price": null,
      "variant": null
    },
    {
      "id": "67b85f8047ee3d81c17bf1a9",
      "advertising_info": null,
      "alcohol_permille": 0,
      "allowed_delivery_methods": [
        "homedelivery",
        "eatin",
        "takeaway"
      ],
      "available_times": [
        {
          "days": [
            1,
            2,
            3,
            4,
            5,
            6,
            7
          ],
          "start_time": 0,
          "end_time": 86400000
        }
      ],
      "barcode_gtin": null,
      "caffeine_info": null,
      "can_be_promoted": {
        "basket": true,
        "venue": true,
        "credits": true
      },
      "checksum": "b126dfdfe06388c1986a528433beb30e",
      "description": "",
      "deposit": null,
      "dietary_preferences": [],
      "disabled_info": null,
      "fulfillment_lead_time": null,
      "has_extra_info": false,
      "images": [
        {
          "url": "https://wolt-menu-images-cdn.wolt.com/menu-images/670399a6a6d89a977ae64330/0307c0c8-f044-11ef-ba78-4a7392c2b6ed_658d32902d.jpg",
          "blurhash": "jzQcXfyp;;GGGGtTpCCpupC8C7yp"
        }
      ],
      "is_cutlery": false,
      "is_no_contact_delivery_allowed": true,
      "is_wolt_plus_only": false,
      "lowest_price": null,
      "lowest_price_v2": null,
      "max_quantity_per_purchase": null,
      "min_quantity_per_purchase": null,
      "name": "NEW NORDIC ნიუ ნორდიკი ჰეა ვოლუმი თმის ზრდისა და მოცულობისთვის ტაბ N30",
      "options": [],
      "original_price": null,
      "price": 13820,
      "purchasable_balance": 4,
      "restrictions": [],
      "return_policy": null,
      "sell_by_weight_config": null,
      "should_display_purchasable_balance": false,
      "tags": [],
      "unit_info": null,
      "unit_price": null,
      "variant": null
    },
    {
      "id": "67b85f8047ee3d81c17bf1ab",
      "advertising_info": null,
      "alcohol_permille": 0,
      "allowed_delivery_methods": [
        "homedelivery",
        "eatin",
        "takeaway"
      ],
      "available_times": [
        {
          "days": [
            1,
            2,
            3,
            4,
            5,
            6,
            7
          ],
          "start_time": 0,
          "end_time": 86400000
        }
      ],
      "barcode_gtin": null,
      "caffeine_info": null,
      "can_be_promoted": {
        "basket": true,
        "venue": true,
        "credits": true
      },
      "checksum": "926666e6f4f74b3a34e38894a87713c6",
      "description": "",
      "deposit": null,
      "dietary_preferences": [],
      "disabled_info": null,
      "fulfillment_lead_time": null,
      "has_extra_info": false,
      "images": [
        {
          "url": "https://wolt-menu-images-cdn.wolt.com/menu-images/670399a6a6d89a977ae64330/0356806e-f044-11ef-a646-c240d485f0e4_6ac9a5d797.jpg",
          "blurhash": "jj:f3ApBT;KHvtxCB3uHgQGGLcll"
        }
      ],
      "is_cutlery": false,
      "is_no_contact_delivery_allowed": true,
      "is_wolt_plus_only": false,
      "lowest_price": null,
      "lowest_price_v2": null,
      "max_quantity_per_purchase": null,
      "min_quantity_per_purchase": null,
      "name": "NEW NORDIC ნიუ ნორდიკი ფოლკეპილენი ძლიერი იმუნიტეტი ტაბ N60",
      "options": [],
      "original_price": null,
      "price": 9882,
      "purchasable_balance": 4,
      "restrictions": [],
      "return_policy": null,
      "sell_by_weight_config": null,
      "should_display_purchasable_balance": false,
      "tags": [],
      "unit_info": null,
      "unit_price": null,
      "variant": null
    },
    {
      "id": "67b85f8047ee3d81c17bf1b2",
      "advertising_info": null,
      "alcohol_permille": 0,
      "allowed_delivery_methods": [
        "homedelivery",
        "eatin",
        "takeaway"
      ],
      "available_times": [
        {
          "days": [
            1,
            2,
            3,
            4,
            5,
            6,
            7
          ],
          "start_time": 0,
          "end_time": 86400000
        }
      ],
      "barcode_gtin": null,
      "caffeine_info": null,
      "can_be_promoted": {
        "basket": true,
        "venue": true,
        "credits": true
      },
      "checksum": "339f9cc5b7c6a019646525a44060f814",
      "description": "",
      "deposit": null,
      "dietary_preferences": [],
      "disabled_info": null,
      "fulfillment_lead_time": null,
      "has_extra_info": false,
      "images": [
        {
          "url": "https://wolt-menu-images-cdn.wolt.com/menu-images/670399a6a6d89a977ae64330/06efb812-f044-11ef-b075-96a22621de7b_776d75678b.jpg",
          "blurhash": "jyVYLbpVX;KGKGBSpCqGlDupKFBT"
        }
      ],
      "is_cutlery": false,
      "is_no_contact_delivery_allowed": true,
      "is_wolt_plus_only": false,
      "lowest_price": null,
      "lowest_price_v2": null,
      "max_quantity_per_purchase": null,
      "min_quantity_per_purchase": null,
      "name": "NEW NORDIC ნიუ ნორდიკი რედ ოილი ახალი თაობის ომეგა3 კაფს N60",
      "options": [],
      "original_price": null,
      "price": 13412,
      "purchasable_balance": 4,
      "restrictions": [],
      "return_policy": null,
      "sell_by_weight_config": null,
      "should_display_purchasable_balance": false,
      "tags": [],
      "unit_info": null,
      "unit_price": null,
      "variant": null
    },
    {
      "id": "67b85f8047ee3d81c17bf1ae",
      "advertising_info": null,
      "alcohol_permille": 0,
      "allowed_delivery_methods": [
        "homedelivery",
        "eatin",
        "takeaway"
      ],
      "available_times": [
        {
          "days": [
            1,
            2,
            3,
            4,
            5,
            6,
            7
          ],
          "start_time": 0,
          "end_time": 86400000
        }
      ],
      "barcode_gtin": null,
      "caffeine_info": null,
      "can_be_promoted": {
        "basket": true,
        "venue": true,
        "credits": true
      },
      "checksum": "fa68764acf7efcedb91374cb85f91f80",
      "description": "",
      "deposit": null,
      "dietary_preferences": [],
      "disabled_info": null,
      "fulfillment_lead_time": null,
      "has_extra_info": false,
      "images": [
        {
          "url": "https://wolt-menu-images-cdn.wolt.com/menu-images/670399a6a6d89a977ae64330/030f395c-f044-11ef-8d6f-aa1c1aefc639_7afbc8b404.jpg",
          "blurhash": "jAOdrEtB;:GXGGpTpDGFBBCquHtC"
        }
      ],
      "is_cutlery": false,
      "is_no_contact_delivery_allowed": true,
      "is_wolt_plus_only": false,
      "lowest_price": null,
      "lowest_price_v2": null,
      "max_quantity_per_purchase": null,
      "min_quantity_per_purchase": null,
      "name": "NEW NORDIC ნიუ ნორდიკი ფიშ ოილი 700მგ ომეგა 3 თევზის ქონი კაფს N60",
      "options": [],
      "original_price": null,
      "price": 7511,
      "purchasable_balance": 4,
      "restrictions": [],
      "return_policy": null,
      "sell_by_weight_config": null,
      "should_display_purchasable_balance": false,
      "tags": [],
      "unit_info": null,
      "unit_price": null,
      "variant": null
    },
    {
      "id": "67b85f8047ee3d81c17bf1aa",
      "advertising_info": null,
      "alcohol_permille": 0,
      "allowed_delivery_methods": [
        "homedelivery",
        "eatin",
        "takeaway"
      ],
      "available_times": [
        {
          "days": [
            1,
            2,
            3,
            4,
            5,
            6,
            7
          ],
          "start_time": 0,
          "end_time": 86400000
        }
      ],
      "barcode_gtin": null,
      "caffeine_info": null,
      "can_be_promoted": {
        "basket": true,
        "venue": true,
        "credits": true
      },
      "checksum": "78300ede1e23187896fb1e0107fd7795",
      "description": "",
      "deposit": null,
      "dietary_preferences": [],
      "disabled_info": null,
      "fulfillment_lead_time": null,
      "has_extra_info": false,
      "images": [
        {
          "url": "https://wolt-menu-images-cdn.wolt.com/menu-images/670399a6a6d89a977ae64330/06d8add4-f044-11ef-95a6-16c88cf09fb9_8627580a79.jpg",
          "blurhash": "jAYtf7lCT;KWKXtTplCGmqGnFSpV"
        }
      ],
      "is_cutlery": false,
      "is_no_contact_delivery_allowed": true,
      "is_wolt_plus_only": false,
      "lowest_price": null,
      "lowest_price_v2": null,
      "max_quantity_per_purchase": null,
      "min_quantity_per_purchase": null,
      "name": "NEW NORDIC ნიუ ნორდიკი-პროსტავიტალი ტაბ.N60",
      "options": [],
      "original_price": null,
      "price": 12812,
      "purchasable_balance": 3,
      "restrictions": [],
      "return_policy": null,
      "sell_by_weight_config": null,
      "should_display_purchasable_balance": false,
      "tags": [],
      "unit_info": null,
      "unit_price": null,
      "variant": null
    },
    {
      "id": "67b85f8047ee3d81c17bf1ac",
      "advertising_info": null,
      "alcohol_permille": 0,
      "allowed_delivery_methods": [
        "homedelivery",
        "eatin",
        "takeaway"
      ],
      "available_times": [
        {
          "days": [
            1,
            2,
            3,
            4,
            5,
            6,
            7
          ],
          "start_time": 0,
          "end_time": 86400000
        }
      ],
      "barcode_gtin": null,
      "caffeine_info": null,
      "can_be_promoted": {
        "basket": true,
        "venue": true,
        "credits": true
      },
      "checksum": "0d1e1dcc51f5e2856171af1d400706ef",
      "description": "",
      "deposit": null,
      "dietary_preferences": [],
      "disabled_info": null,
      "fulfillment_lead_time": null,
      "has_extra_info": false,
      "images": [
        {
          "url": "https://wolt-menu-images-cdn.wolt.com/menu-images/670399a6a6d89a977ae64330/06fd968a-f044-11ef-9bea-e605225ca122_a0d4387b48.jpg",
          "blurhash": "jBQJX7tq;;GSqCGGFWpCpquCGTFG"
        }
      ],
      "is_cutlery": false,
      "is_no_contact_delivery_allowed": true,
      "is_wolt_plus_only": false,
      "lowest_price": null,
      "lowest_price_v2": null,
      "max_quantity_per_purchase": null,
      "min_quantity_per_purchase": null,
      "name": "NEW NORDIC ნიუ ნორდიკი სმენის და სისხლის მიმოქცევის გაუმჯობესება ტაბ N60",
      "options": [],
      "original_price": null,
      "price": 12311,
      "purchasable_balance": 4,
      "restrictions": [],
      "return_policy": null,
      "sell_by_weight_config": null,
      "should_display_purchasable_balance": false,
      "tags": [],
      "unit_info": null,
      "unit_price": null,
      "variant": null
    },
    {
      "id": "67b85f8047ee3d81c17bf1ad",
      "advertising_info": null,
      "alcohol_permille": 0,
      "allowed_delivery_methods": [
        "homedelivery",
        "eatin",
        "takeaway"
      ],
      "available_times": [
        {
          "days": [
            1,
            2,
            3,
            4,
            5,
            6,
            7
          ],
          "start_time": 0,
          "end_time": 86400000
        }
      ],
      "barcode_gtin": null,
      "caffeine_info": null,
      "can_be_promoted": {
        "basket": true,
        "venue": true,
        "credits": true
      },
      "checksum": "13ed58f7a34279b9172276162b066d22",
      "description": "",
      "deposit": null,
      "dietary_preferences": [],
      "disabled_info": null,
      "fulfillment_lead_time": null,
      "has_extra_info": false,
      "images": [
        {
          "url": "https://wolt-menu-images-cdn.wolt.com/menu-images/670399a6a6d89a977ae64330/06d1cb90-f044-11ef-854e-5e537071aa85_ca855ed7a8.jpg",
          "blurhash": "jAZdjapUT;GGCGBTtCuGlGGpKmpV"
        }
      ],
      "is_cutlery": false,
      "is_no_contact_delivery_allowed": true,
      "is_wolt_plus_only": false,
      "lowest_price": null,
      "lowest_price_v2": null,
      "max_quantity_per_purchase": null,
      "min_quantity_per_purchase": null,
      "name": "NEW NORDIC ნიუ ნორდიკი სისხლში გლუკოზის კონტროლი ტაბ N60",
      "options": [],
      "original_price": null,
      "price": 8842,
      "purchasable_balance": 2,
      "restrictions": [],
      "return_policy": null,
      "sell_by_weight_config": null,
      "should_display_purchasable_balance": false,
      "tags": [],
      "unit_info": null,
      "unit_price": null,
      "variant": null
    },
    {
      "id": "67b85f8047ee3d81c17bf1af",
      "advertising_info": null,
      "alcohol_permille": 0,
      "allowed_delivery_methods": [
        "homedelivery",
        "eatin",
        "takeaway"
      ],
      "available_times": [
        {
          "days": [
            1,
            2,
            3,
            4,
            5,
            6,
            7
          ],
          "start_time": 0,
          "end_time": 86400000
        }
      ],
      "barcode_gtin": null,
      "caffeine_info": null,
      "can_be_promoted": {
        "basket": true,
        "venue": true,
        "credits": true
      },
      "checksum": "17386c38133d6a6c164f9b4ad3e06224",
      "description": "",
      "deposit": null,
      "dietary_preferences": [],
      "disabled_info": null,
      "fulfillment_lead_time": null,
      "has_extra_info": false,
      "images": [
        {
          "url": "https://wolt-menu-images-cdn.wolt.com/menu-images/670399a6a6d89a977ae64330/0c10e6ae-f044-11ef-8726-de4de06eb748_d53e116458.jpg",
          "blurhash": "jzWY;eupX;GGGGBTpCyqlWGpKnpT"
        }
      ],
      "is_cutlery": false,
      "is_no_contact_delivery_allowed": true,
      "is_wolt_plus_only": false,
      "lowest_price": null,
      "lowest_price_v2": null,
      "max_quantity_per_purchase": null,
      "min_quantity_per_purchase": null,
      "name": "NEW NORDIC ნიუ ნორდიკი ქრან ბერი შარდ-სასქესო სისტემის სიჯანსაღე ტაბ N30",
      "options": [],
      "original_price": null,
      "price": 10931,
      "purchasable_balance": 4,
      "restrictions": [],
      "return_policy": null,
      "sell_by_weight_config": null,
      "should_display_purchasable_balance": false,
      "tags": [],
      "unit_info": null,
      "unit_price": null,
      "variant": null
    },
    {
      "id": "67b85f8047ee3d81c17bf1b0",
      "advertising_info": null,
      "alcohol_permille": 0,
      "allowed_delivery_methods": [
        "homedelivery",
        "eatin",
        "takeaway"
      ],
      "available_times": [
        {
          "days": [
            1,
            2,
            3,
            4,
            5,
            6,
            7
          ],
          "start_time": 0,
          "end_time": 86400000
        }
      ],
      "barcode_gtin": null,
      "caffeine_info": null,
      "can_be_promoted": {
        "basket": true,
        "venue": true,
        "credits": true
      },
      "checksum": "d85a791facab7ce66e98678c69344fbe",
      "description": "",
      "deposit": null,
      "dietary_preferences": [],
      "disabled_info": null,
      "fulfillment_lead_time": null,
      "has_extra_info": false,
      "images": [
        {
          "url": "https://wolt-menu-images-cdn.wolt.com/menu-images/670399a6a6d89a977ae64330/0c00e92a-f044-11ef-bfd6-5e2d1e41efcb_e0ac7c1f05.jpg",
          "blurhash": "jAQYLjtT;;GGGGtTpCGGqnCpFVtT"
        }
      ],
      "is_cutlery": false,
      "is_no_contact_delivery_allowed": true,
      "is_wolt_plus_only": false,
      "lowest_price": null,
      "lowest_price_v2": null,
      "max_quantity_per_purchase": null,
      "min_quantity_per_purchase": null,
      "name": "NEW NORDIC ნიუ ნორდიკი ბლუ ბერი აიბრაითი მხედველობის სიმახვილე ტაბ N60",
      "options": [],
      "original_price": null,
      "price": 8752,
      "purchasable_balance": 4,
      "restrictions": [],
      "return_policy": null,
      "sell_by_weight_config": null,
      "should_display_purchasable_balance": false,
      "tags": [],
      "unit_info": null,
      "unit_price": null,
      "variant": null
    }
  ],
  "options": [],
  "variant_groups": [],
  "metadata": {
    "next_page_token": null,
    "page": 1
  }
}