{
  "category": {
    "id": "67af3aabf3f7826e594e64da",
    "description": "",
    "images": [
      {
        "url": "https://wolt-menu-images-cdn.wolt.com/menu-images/60ab4285dbd114f0b9139395/6cdb7b16-ead1-11ef-a356-82ef38b1a834_14378736_eabb_11ef_a7ba_ce0af23153c2_el.jpg",
        "blurhash": "j3Wd7HTJZf8iIOcP40XK40OYKk8O"
      }
    ],
    "name": "ტექნიკა",
    "slug": "menucategory-448"
  },
  "categories": [
    {
      "id": "67af3aabf3f7826e594e64da",
      "item_ids": [
        "67af3aeb118084a25eb60bda",
        "67af3aeeac67a9e7d4e1cadb",
        "67af3af28328543d16037ef9",
        "67af3af4c7e7257a314ffcd2",
        "67af3af75033f1fa485c6687",
        "67af3af99ead0723021f2b8f",
        "67af3afccbc882d8739767a1",
        "67af3afe5e2d717ac39a6d95",
        "67af3b02d66b41a7bdfd3b69",
        "67af3b06dc8a7b08b224104a",
        "67af3b08ca107843ad2e7f26",
        "67af3b0c9212affa4add84bb",
        "67af3b118ef96473e3ded5bd",
        "67af3b1429d4c5ddae094350",
        "67af3b171c4677d0f714bc89",
        "67af3b1a76d7a9adb4982ed6",
        "67af3b1d0790ca59a0107ad1",
        "67af3b22ac95be1f02d7ec46",
        "67af3b2583422be1b70d3260",
        "67af3b292e801b8e9da38bc2",
        "67af3b2b29d4c5ddae094356",
        "67af3b2ee557160fb188df2c",
        "67af3b302992138af694f41c",
        "67af3b3476d7a9adb4982ee2",
        "67af3b375ae06b2da22ef91b",
        "67af3b398907ebb6f4216e2d",
        "67af3b3cac95be1f02d7ec4e",
        "67af3b3e1fa00330fdc28652",
        "67af3b403cbb74d2141ee20c",
        "67af3b433aec4e5a3e0b339e",
        "67af3b46ee76f294b9eae878",
        "67af3b48b66519af3cecf91f",
        "67af3b4ad66b41a7bdfd3b89",
        "67af3b4c44617e6cbfdf8b53",
        "67af3b4f5033f1fa485c66af",
        "67af3b5260b3805a2bdf5b9b",
        "67af3b5663e91c5686568b95",
        "67af3b5a93af4d034f071150",
        "67af3b5c44985dd211e9654d",
        "67af3b5fdfb8da44546c67ee",
        "67af3b620fe4403d6581b70a",
        "67af3b6693af4d034f07115f",
        "67af3b6a0fe4403d6581b715",
        "67af3b6e2e475465982e87a5",
        "67af3b70d4b6e1dc4f9a1917",
        "67af3b7389cd8ed07ab6d1a2",
        "67af3b760681df437b75b1b1",
        "67af3b798328543d16037f21",
        "67af3b7c44617e6cbfdf8b7d",
        "67af3b7ff3f7826e594e6522"
      ]
    }
  ],
  "items": [
    {
      "id": "67af3aeb118084a25eb60bda",
      "advertising_info": null,
      "alcohol_permille": 0,
      "allowed_delivery_methods": [
        "homedelivery",
        "eatin",
        "takeaway"
      ],
      "available_times": [
        {
          "days": [
            1,
            2,
            3,
            4,
            5,
            6,
            7
          ],
          "start_time": 0,
          "end_time": 86400000
        }
      ],
      "barcode_gtin": "8004399325067",
      "caffeine_info": null,
      "can_be_promoted": {
        "basket": true,
        "venue": true,
        "credits": true
      },
      "checksum": "70b9377c5925b0093174940abcb7cd09",
      "description": "",
      "deposit": null,
      "dietary_preferences": [],
      "disabled_info": null,
      "fulfillment_lead_time": null,
      "has_extra_info": false,
      "images": [
        {
          "url": "https://wolt-menu-images-cdn.wolt.com/menu-images/5eb50a8743ef4f7e46644db9/502086b0-ead1-11ef-afb5-860a16ce2a4d_353875.jpg",
          "blurhash": "j5:vDVCp;;KXKXtTpCCp;;GG4hll"
        }
      ],
      "is_cutlery": false,
      "is_no_contact_delivery_allowed": true,
      "is_wolt_plus_only": false,
      "lowest_price": null,
      "lowest_price_v2": null,
      "max_quantity_per_purchase": null,
      "min_quantity_per_purchase": null,
      "name": "DELONGHI ყავის აპარატი ECAM22.110.SB/8004399325067",
      "options": [],
      "original_price": null,
      "price": 201500,
      "purchasable_balance": null,
      "restrictions": [],
      "return_policy": null,
      "sell_by_weight_config": null,
      "should_display_purchasable_balance": false,
      "tags": [],
      "unit_info": null,
      "unit_price": null,
      "variant": null
    },
    {
      "id": "67af3aeeac67a9e7d4e1cadb",
      "advertising_info": null,
      "alcohol_permille": 0,
      "allowed_delivery_methods": [
        "homedelivery",
        "eatin",
        "takeaway"
      ],
      "available_times": [
        {
          "days": [
            1,
            2,
            3,
            4,
            5,
            6,
            7
          ],
          "start_time": 0,
          "end_time": 86400000
        }
      ],
      "barcode_gtin": "8021098002518",
      "caffeine_info": null,
      "can_be_promoted": {
        "basket": true,
        "venue": true,
        "credits": true
      },
      "checksum": "37df43ad98e1b59897f41bd78860c54c",
      "description": "",
      "deposit": null,
      "dietary_preferences": [],
      "disabled_info": null,
      "fulfillment_lead_time": null,
      "has_extra_info": false,
      "images": [
        {
          "url": "https://wolt-menu-images-cdn.wolt.com/menu-images/5eb50a8743ef4f7e46644db9/50211b7a-ead1-11ef-858f-f27e7ca2e507_351868.jpg",
          "blurhash": "j5:vDWGG;;GFy7tTGGCp;;tT41GG"
        }
      ],
      "is_cutlery": false,
      "is_no_contact_delivery_allowed": true,
      "is_wolt_plus_only": false,
      "lowest_price": null,
      "lowest_price_v2": null,
      "max_quantity_per_purchase": null,
      "min_quantity_per_purchase": null,
      "name": "BRAUN MULTI გრილი CG9047/8021098002518",
      "options": [],
      "original_price": null,
      "price": 79900,
      "purchasable_balance": null,
      "restrictions": [],
      "return_policy": null,
      "sell_by_weight_config": null,
      "should_display_purchasable_balance": false,
      "tags": [],
      "unit_info": null,
      "unit_price": null,
      "variant": null
    },
    {
      "id": "67af3af28328543d16037ef9",
      "advertising_info": null,
      "alcohol_permille": 0,
      "allowed_delivery_methods": [
        "homedelivery",
        "eatin",
        "takeaway"
      ],
      "available_times": [
        {
          "days": [
            1,
            2,
            3,
            4,
            5,
            6,
            7
          ],
          "start_time": 0,
          "end_time": 86400000
        }
      ],
      "barcode_gtin": "195949036019",
      "caffeine_info": null,
      "can_be_promoted": {
        "basket": true,
        "venue": true,
        "credits": true
      },
      "checksum": "d69d55f5d3c80e5a2105be060dedbc76",
      "description": "",
      "deposit": null,
      "dietary_preferences": [],
      "disabled_info": {
        "disable_text": "Sold out",
        "disable_reason": null
      },
      "fulfillment_lead_time": null,
      "has_extra_info": false,
      "images": [
        {
          "url": "https://wolt-menu-images-cdn.wolt.com/menu-images/5eb50a8743ef4f7e46644db9/453a2b02-ead1-11ef-895e-2655e86c8b3c_331868.jpg",
          "blurhash": "jaZfjQll;;TtpCCpKGtT;;KX4yh4"
        }
      ],
      "is_cutlery": false,
      "is_no_contact_delivery_allowed": true,
      "is_wolt_plus_only": false,
      "lowest_price": null,
      "lowest_price_v2": null,
      "max_quantity_per_purchase": null,
      "min_quantity_per_purchase": null,
      "name": "IPHONE 15 128გბ შავი/195949036019",
      "options": [],
      "original_price": null,
      "price": 229900,
      "purchasable_balance": 0,
      "restrictions": [],
      "return_policy": null,
      "sell_by_weight_config": null,
      "should_display_purchasable_balance": false,
      "tags": [],
      "unit_info": null,
      "unit_price": null,
      "variant": null
    },
    {
      "id": "67af3af4c7e7257a314ffcd2",
      "advertising_info": null,
      "alcohol_permille": 0,
      "allowed_delivery_methods": [
        "homedelivery",
        "eatin",
        "takeaway"
      ],
      "available_times": [
        {
          "days": [
            1,
            2,
            3,
            4,
            5,
            6,
            7
          ],
          "start_time": 0,
          "end_time": 86400000
        }
      ],
      "barcode_gtin": "7636248706096",
      "caffeine_info": null,
      "can_be_promoted": {
        "basket": true,
        "venue": true,
        "credits": true
      },
      "checksum": "437696a41ca70ef0a640bbd5125c204a",
      "description": "",
      "deposit": null,
      "dietary_preferences": [],
      "disabled_info": null,
      "fulfillment_lead_time": null,
      "has_extra_info": false,
      "images": [
        {
          "url": "https://wolt-menu-images-cdn.wolt.com/menu-images/5eb50a8743ef4f7e46644db9/4db38d64-ead1-11ef-b2a4-be67328f8fa1_346821.jpg",
          "blurhash": "j4:LHWKX;;tTKXtTpCGG;;pC00GG"
        }
      ],
      "is_cutlery": false,
      "is_no_contact_delivery_allowed": true,
      "is_wolt_plus_only": false,
      "lowest_price": null,
      "lowest_price_v2": null,
      "max_quantity_per_purchase": null,
      "min_quantity_per_purchase": null,
      "name": "SOLLEX გრილი SL345 2000W/7636248706096",
      "options": [],
      "original_price": null,
      "price": 16900,
      "purchasable_balance": null,
      "restrictions": [],
      "return_policy": null,
      "sell_by_weight_config": null,
      "should_display_purchasable_balance": false,
      "tags": [],
      "unit_info": null,
      "unit_price": null,
      "variant": null
    },
    {
      "id": "67af3af75033f1fa485c6687",
      "advertising_info": null,
      "alcohol_permille": 0,
      "allowed_delivery_methods": [
        "homedelivery",
        "eatin",
        "takeaway"
      ],
      "available_times": [
        {
          "days": [
            1,
            2,
            3,
            4,
            5,
            6,
            7
          ],
          "start_time": 0,
          "end_time": 86400000
        }
      ],
      "barcode_gtin": "8025569127182",
      "caffeine_info": null,
      "can_be_promoted": {
        "basket": true,
        "venue": true,
        "credits": true
      },
      "checksum": "b66c39e831f4438f20795e74f8889016",
      "description": "",
      "deposit": null,
      "dietary_preferences": [],
      "disabled_info": null,
      "fulfillment_lead_time": null,
      "has_extra_info": false,
      "images": [
        {
          "url": "https://wolt-menu-images-cdn.wolt.com/menu-images/5eb50a8743ef4f7e46644db9/37aff480-ead1-11ef-870a-eab9f01fb128_241123.jpg",
          "blurhash": "j5:vDVGG;;BTPcGGh4ll;;tD4hGX"
        }
      ],
      "is_cutlery": false,
      "is_no_contact_delivery_allowed": true,
      "is_wolt_plus_only": false,
      "lowest_price": null,
      "lowest_price_v2": null,
      "max_quantity_per_purchase": null,
      "min_quantity_per_purchase": null,
      "name": "SOLLEX წვენსაწური SL515/8025569127182",
      "options": [],
      "original_price": null,
      "price": 24900,
      "purchasable_balance": null,
      "restrictions": [],
      "return_policy": null,
      "sell_by_weight_config": null,
      "should_display_purchasable_balance": false,
      "tags": [],
      "unit_info": null,
      "unit_price": null,
      "variant": null
    },
    {
      "id": "67af3af99ead0723021f2b8f",
      "advertising_info": null,
      "alcohol_permille": 0,
      "allowed_delivery_methods": [
        "homedelivery",
        "eatin",
        "takeaway"
      ],
      "available_times": [
        {
          "days": [
            1,
            2,
            3,
            4,
            5,
            6,
            7
          ],
          "start_time": 0,
          "end_time": 86400000
        }
      ],
      "barcode_gtin": "6939962755861",
      "caffeine_info": null,
      "can_be_promoted": {
        "basket": true,
        "venue": true,
        "credits": true
      },
      "checksum": "a803706605d5a4bee8c72f81f9102b80",
      "description": "",
      "deposit": null,
      "dietary_preferences": [],
      "disabled_info": null,
      "fulfillment_lead_time": null,
      "has_extra_info": false,
      "images": [
        {
          "url": "https://wolt-menu-images-cdn.wolt.com/menu-images/5eb50a8743ef4f7e46644db9/426bc46c-ead1-11ef-a91e-9a5d917a3b19_288900.jpg",
          "blurhash": "j7Z;vTGG;;CpxSy8GGC8;;tT4hGG"
        }
      ],
      "is_cutlery": false,
      "is_no_contact_delivery_allowed": true,
      "is_wolt_plus_only": false,
      "lowest_price": null,
      "lowest_price_v2": null,
      "max_quantity_per_purchase": null,
      "min_quantity_per_purchase": null,
      "name": "MIDEA მულტი ქვაბი FS5077 1.8L შავი/6939962755861",
      "options": [],
      "original_price": null,
      "price": 19900,
      "purchasable_balance": null,
      "restrictions": [],
      "return_policy": null,
      "sell_by_weight_config": null,
      "should_display_purchasable_balance": false,
      "tags": [],
      "unit_info": null,
      "unit_price": null,
      "variant": null
    },
    {
      "id": "67af3afccbc882d8739767a1",
      "advertising_info": null,
      "alcohol_permille": 0,
      "allowed_delivery_methods": [
        "homedelivery",
        "eatin",
        "takeaway"
      ],
      "available_times": [
        {
          "days": [
            1,
            2,
            3,
            4,
            5,
            6,
            7
          ],
          "start_time": 0,
          "end_time": 86400000
        }
      ],
      "barcode_gtin": "3037444641497",
      "caffeine_info": null,
      "can_be_promoted": {
        "basket": true,
        "venue": true,
        "credits": true
      },
      "checksum": "6bfe493382992c84c29e44f1431ee935",
      "description": "",
      "deposit": null,
      "dietary_preferences": [],
      "disabled_info": null,
      "fulfillment_lead_time": null,
      "has_extra_info": false,
      "images": [
        {
          "url": "https://wolt-menu-images-cdn.wolt.com/menu-images/5eb50a8743ef4f7e46644db9/47dbff48-ead1-11ef-ac96-b2e4f1f78c9e_335322.jpg",
          "blurhash": "j4:LLXlm;;TcTttTcQCqXKKW8yh5"
        }
      ],
      "is_cutlery": false,
      "is_no_contact_delivery_allowed": true,
      "is_wolt_plus_only": false,
      "lowest_price": null,
      "lowest_price_v2": null,
      "max_quantity_per_purchase": null,
      "min_quantity_per_purchase": null,
      "name": "ILITEK ბლენდერ IL4149 800W/3037444641497",
      "options": [],
      "original_price": null,
      "price": 8990,
      "purchasable_balance": null,
      "restrictions": [],
      "return_policy": null,
      "sell_by_weight_config": null,
      "should_display_purchasable_balance": false,
      "tags": [],
      "unit_info": null,
      "unit_price": null,
      "variant": null
    },
    {
      "id": "67af3afe5e2d717ac39a6d95",
      "advertising_info": null,
      "alcohol_permille": 0,
      "allowed_delivery_methods": [
        "homedelivery",
        "eatin",
        "takeaway"
      ],
      "available_times": [
        {
          "days": [
            1,
            2,
            3,
            4,
            5,
            6,
            7
          ],
          "start_time": 0,
          "end_time": 86400000
        }
      ],
      "barcode_gtin": "4065544152567",
      "caffeine_info": null,
      "can_be_promoted": {
        "basket": true,
        "venue": true,
        "credits": true
      },
      "checksum": "7bead63d8555c4977f034f183c10a1f1",
      "description": "",
      "deposit": null,
      "dietary_preferences": [],
      "disabled_info": null,
      "fulfillment_lead_time": null,
      "has_extra_info": false,
      "images": [
        {
          "url": "https://wolt-menu-images-cdn.wolt.com/menu-images/5eb50a8743ef4f7e46644db9/47db0b38-ead1-11ef-802a-f277f9bf0e6e_336999.jpg",
          "blurhash": "j5:vDVGG;;pCGGGGGGll;;pC00GG"
        }
      ],
      "is_cutlery": false,
      "is_no_contact_delivery_allowed": true,
      "is_wolt_plus_only": false,
      "lowest_price": null,
      "lowest_price_v2": null,
      "max_quantity_per_purchase": null,
      "min_quantity_per_purchase": null,
      "name": "FRANKO ინდუქციური COOKER FIH-1234/4065544152567",
      "options": [],
      "original_price": null,
      "price": 13900,
      "purchasable_balance": null,
      "restrictions": [],
      "return_policy": null,
      "sell_by_weight_config": null,
      "should_display_purchasable_balance": false,
      "tags": [],
      "unit_info": null,
      "unit_price": null,
      "variant": null
    },
    {
      "id": "67af3b02d66b41a7bdfd3b69",
      "advertising_info": null,
      "alcohol_permille": 0,
      "allowed_delivery_methods": [
        "homedelivery",
        "eatin",
        "takeaway"
      ],
      "available_times": [
        {
          "days": [
            1,
            2,
            3,
            4,
            5,
            6,
            7
          ],
          "start_time": 0,
          "end_time": 86400000
        }
      ],
      "barcode_gtin": "6933310520804",
      "caffeine_info": null,
      "can_be_promoted": {
        "basket": true,
        "venue": true,
        "credits": true
      },
      "checksum": "56424cea81e5d7b0f915c482d1685b35",
      "description": "",
      "deposit": null,
      "dietary_preferences": [],
      "disabled_info": null,
      "fulfillment_lead_time": null,
      "has_extra_info": false,
      "images": [
        {
          "url": "https://wolt-menu-images-cdn.wolt.com/menu-images/5eb50a8743ef4f7e46644db9/424aac96-ead1-11ef-b935-0e8453035962_297628.jpg",
          "blurhash": "j5:vHWKX;;lkGGGGuGll;:ll4yPc"
        }
      ],
      "is_cutlery": false,
      "is_no_contact_delivery_allowed": true,
      "is_wolt_plus_only": false,
      "lowest_price": null,
      "lowest_price_v2": null,
      "max_quantity_per_purchase": null,
      "min_quantity_per_purchase": null,
      "name": "ILITEK ელექტრო ჩაიდანი IL1019 /6933310520804",
      "options": [],
      "original_price": null,
      "price": 4990,
      "purchasable_balance": null,
      "restrictions": [],
      "return_policy": null,
      "sell_by_weight_config": null,
      "should_display_purchasable_balance": false,
      "tags": [],
      "unit_info": null,
      "unit_price": null,
      "variant": null
    },
    {
      "id": "67af3b06dc8a7b08b224104a",
      "advertising_info": null,
      "alcohol_permille": 0,
      "allowed_delivery_methods": [
        "homedelivery",
        "eatin",
        "takeaway"
      ],
      "available_times": [
        {
          "days": [
            1,
            2,
            3,
            4,
            5,
            6,
            7
          ],
          "start_time": 0,
          "end_time": 86400000
        }
      ],
      "barcode_gtin": "8021098772336",
      "caffeine_info": null,
      "can_be_promoted": {
        "basket": true,
        "venue": true,
        "credits": true
      },
      "checksum": "f27388c2270b64fa242a16c42733f02e",
      "description": "",
      "deposit": null,
      "dietary_preferences": [],
      "disabled_info": null,
      "fulfillment_lead_time": null,
      "has_extra_info": false,
      "images": [
        {
          "url": "https://wolt-menu-images-cdn.wolt.com/menu-images/5eb50a8743ef4f7e46644db9/3a6a52e2-ead1-11ef-a941-8aafefefcb03_249158.jpg",
          "blurhash": "j5:vDWtT;;KXPcGGllll;;GG4hll"
        }
      ],
      "is_cutlery": false,
      "is_no_contact_delivery_allowed": true,
      "is_wolt_plus_only": false,
      "lowest_price": null,
      "lowest_price_v2": null,
      "max_quantity_per_purchase": null,
      "min_quantity_per_purchase": null,
      "name": "BRAUN ბლენდერი JB3100BK 800W 1.5L/8021098772336",
      "options": [],
      "original_price": null,
      "price": 26900,
      "purchasable_balance": null,
      "restrictions": [],
      "return_policy": null,
      "sell_by_weight_config": null,
      "should_display_purchasable_balance": false,
      "tags": [],
      "unit_info": null,
      "unit_price": null,
      "variant": null
    },
    {
      "id": "67af3b08ca107843ad2e7f26",
      "advertising_info": null,
      "alcohol_permille": 0,
      "allowed_delivery_methods": [
        "homedelivery",
        "eatin",
        "takeaway"
      ],
      "available_times": [
        {
          "days": [
            1,
            2,
            3,
            4,
            5,
            6,
            7
          ],
          "start_time": 0,
          "end_time": 86400000
        }
      ],
      "barcode_gtin": "2000000055459",
      "caffeine_info": null,
      "can_be_promoted": {
        "basket": true,
        "venue": true,
        "credits": true
      },
      "checksum": "0f03f1c26b30a08cbf493e45d8db47f4",
      "description": "",
      "deposit": null,
      "dietary_preferences": [],
      "disabled_info": null,
      "fulfillment_lead_time": null,
      "has_extra_info": false,
      "images": [
        {
          "url": "https://wolt-menu-images-cdn.wolt.com/menu-images/5eb50a8743ef4f7e46644db9/3ed0093a-ead1-11ef-a322-0e8453035962_278445.jpg",
          "blurhash": "j7:fzUtC;;KXPcCphlpC;;GG4hpl"
        }
      ],
      "is_cutlery": false,
      "is_no_contact_delivery_allowed": true,
      "is_wolt_plus_only": false,
      "lowest_price": null,
      "lowest_price_v2": null,
      "max_quantity_per_purchase": null,
      "min_quantity_per_purchase": null,
      "name": "MIDEA მტვერსასრუტი MGE13A ORANGE 2200ვ/2000000055459",
      "options": [],
      "original_price": null,
      "price": 24900,
      "purchasable_balance": null,
      "restrictions": [],
      "return_policy": null,
      "sell_by_weight_config": null,
      "should_display_purchasable_balance": false,
      "tags": [],
      "unit_info": null,
      "unit_price": null,
      "variant": null
    },
    {
      "id": "67af3b0c9212affa4add84bb",
      "advertising_info": null,
      "alcohol_permille": 0,
      "allowed_delivery_methods": [
        "homedelivery",
        "eatin",
        "takeaway"
      ],
      "available_times": [
        {
          "days": [
            1,
            2,
            3,
            4,
            5,
            6,
            7
          ],
          "start_time": 0,
          "end_time": 86400000
        }
      ],
      "barcode_gtin": "4055555550544",
      "caffeine_info": null,
      "can_be_promoted": {
        "basket": true,
        "venue": true,
        "credits": true
      },
      "checksum": "e88aa846cbb48313dd35eb387072038f",
      "description": "",
      "deposit": null,
      "dietary_preferences": [],
      "disabled_info": null,
      "fulfillment_lead_time": null,
      "has_extra_info": false,
      "images": [
        {
          "url": "https://wolt-menu-images-cdn.wolt.com/menu-images/5eb50a8743ef4f7e46644db9/34ebfaaa-ead1-11ef-96ee-12ab05747dad_200919.jpg",
          "blurhash": "j6:fzUKX;;h4TtpCh4KX;;ll4hPc"
        }
      ],
      "is_cutlery": false,
      "is_no_contact_delivery_allowed": true,
      "is_wolt_plus_only": false,
      "lowest_price": null,
      "lowest_price_v2": null,
      "max_quantity_per_purchase": null,
      "min_quantity_per_purchase": null,
      "name": "FRANKO ხორცსაკეპი FMG-1113 3500W/4055555550544",
      "options": [],
      "original_price": null,
      "price": 31900,
      "purchasable_balance": null,
      "restrictions": [],
      "return_policy": null,
      "sell_by_weight_config": null,
      "should_display_purchasable_balance": false,
      "tags": [],
      "unit_info": null,
      "unit_price": null,
      "variant": null
    },
    {
      "id": "67af3b118ef96473e3ded5bd",
      "advertising_info": null,
      "alcohol_permille": 0,
      "allowed_delivery_methods": [
        "homedelivery",
        "eatin",
        "takeaway"
      ],
      "available_times": [
        {
          "days": [
            1,
            2,
            3,
            4,
            5,
            6,
            7
          ],
          "start_time": 0,
          "end_time": 86400000
        }
      ],
      "barcode_gtin": "4055555550124",
      "caffeine_info": null,
      "can_be_promoted": {
        "basket": true,
        "venue": true,
        "credits": true
      },
      "checksum": "93f0a7f4bff0c46780b1f33a81894841",
      "description": "",
      "deposit": null,
      "dietary_preferences": [],
      "disabled_info": null,
      "fulfillment_lead_time": null,
      "has_extra_info": false,
      "images": [
        {
          "url": "https://wolt-menu-images-cdn.wolt.com/menu-images/5eb50a8743ef4f7e46644db9/31d764a8-ead1-11ef-af17-263763f20541_154569.jpg",
          "blurhash": "j7Z;vTGG;;GGCntTGGCp;;GG40pC"
        }
      ],
      "is_cutlery": false,
      "is_no_contact_delivery_allowed": true,
      "is_wolt_plus_only": false,
      "lowest_price": null,
      "lowest_price_v2": null,
      "max_quantity_per_purchase": null,
      "min_quantity_per_purchase": null,
      "name": "FRANKO ელექტრო საცხობი F-EO1092 38L /4055555550124",
      "options": [],
      "original_price": null,
      "price": 19900,
      "purchasable_balance": null,
      "restrictions": [],
      "return_policy": null,
      "sell_by_weight_config": null,
      "should_display_purchasable_balance": false,
      "tags": [],
      "unit_info": null,
      "unit_price": null,
      "variant": null
    },
    {
      "id": "67af3b1429d4c5ddae094350",
      "advertising_info": null,
      "alcohol_permille": 0,
      "allowed_delivery_methods": [
        "homedelivery",
        "eatin",
        "takeaway"
      ],
      "available_times": [
        {
          "days": [
            1,
            2,
            3,
            4,
            5,
            6,
            7
          ],
          "start_time": 0,
          "end_time": 86400000
        }
      ],
      "barcode_gtin": "6987210893124",
      "caffeine_info": null,
      "can_be_promoted": {
        "basket": true,
        "venue": true,
        "credits": true
      },
      "checksum": "f8b2f6119a05168a198e157f629723c6",
      "description": "",
      "deposit": null,
      "dietary_preferences": [],
      "disabled_info": null,
      "fulfillment_lead_time": null,
      "has_extra_info": false,
      "images": [
        {
          "url": "https://wolt-menu-images-cdn.wolt.com/menu-images/5eb50a8743ef4f7e46644db9/4da7905e-ead1-11ef-aa4a-be41a433f110_346820.jpg",
          "blurhash": "j6:vDVCp;;KXKXtTllCp;;GG4hpC"
        }
      ],
      "is_cutlery": false,
      "is_no_contact_delivery_allowed": true,
      "is_wolt_plus_only": false,
      "lowest_price": null,
      "lowest_price_v2": null,
      "max_quantity_per_purchase": null,
      "min_quantity_per_purchase": null,
      "name": "ILITEK ყავის აპარატი IL4349 600W/6987210893124",
      "options": [],
      "original_price": null,
      "price": 5990,
      "purchasable_balance": null,
      "restrictions": [],
      "return_policy": null,
      "sell_by_weight_config": null,
      "should_display_purchasable_balance": false,
      "tags": [],
      "unit_info": null,
      "unit_price": null,
      "variant": null
    },
    {
      "id": "67af3b171c4677d0f714bc89",
      "advertising_info": null,
      "alcohol_permille": 0,
      "allowed_delivery_methods": [
        "homedelivery",
        "eatin",
        "takeaway"
      ],
      "available_times": [
        {
          "days": [
            1,
            2,
            3,
            4,
            5,
            6,
            7
          ],
          "start_time": 0,
          "end_time": 86400000
        }
      ],
      "barcode_gtin": "8021098772343",
      "caffeine_info": null,
      "can_be_promoted": {
        "basket": true,
        "venue": true,
        "credits": true
      },
      "checksum": "45a398fffb14ffd921b1c174eea564d0",
      "description": "",
      "deposit": null,
      "dietary_preferences": [],
      "disabled_info": null,
      "fulfillment_lead_time": null,
      "has_extra_info": false,
      "images": [
        {
          "url": "https://wolt-menu-images-cdn.wolt.com/menu-images/5eb50a8743ef4f7e46644db9/3a8d53be-ead1-11ef-be6a-263763f20541_265730.jpg",
          "blurhash": "j3:;LXGG;;KGllGGPcpC;;tT4hCp"
        }
      ],
      "is_cutlery": false,
      "is_no_contact_delivery_allowed": true,
      "is_wolt_plus_only": false,
      "lowest_price": null,
      "lowest_price_v2": null,
      "max_quantity_per_purchase": null,
      "min_quantity_per_purchase": null,
      "name": "BRAUN ბლენდერი JB3100WH/8021098772343",
      "options": [],
      "original_price": null,
      "price": 26900,
      "purchasable_balance": null,
      "restrictions": [],
      "return_policy": null,
      "sell_by_weight_config": null,
      "should_display_purchasable_balance": false,
      "tags": [],
      "unit_info": null,
      "unit_price": null,
      "variant": null
    },
    {
      "id": "67af3b1a76d7a9adb4982ed6",
      "advertising_info": null,
      "alcohol_permille": 0,
      "allowed_delivery_methods": [
        "homedelivery",
        "eatin",
        "takeaway"
      ],
      "available_times": [
        {
          "days": [
            1,
            2,
            3,
            4,
            5,
            6,
            7
          ],
          "start_time": 0,
          "end_time": 86400000
        }
      ],
      "barcode_gtin": "4055544451395",
      "caffeine_info": null,
      "can_be_promoted": {
        "basket": true,
        "venue": true,
        "credits": true
      },
      "checksum": "bbea3a2922a3d73e6a26625af00fb422",
      "description": "",
      "deposit": null,
      "dietary_preferences": [],
      "disabled_info": null,
      "fulfillment_lead_time": null,
      "has_extra_info": false,
      "images": [
        {
          "url": "https://wolt-menu-images-cdn.wolt.com/menu-images/5eb50a8743ef4f7e46644db9/3a6ac7d6-ead1-11ef-a971-42a61c5f78e0_263554.jpg",
          "blurhash": "j3:;LXll;;TtPcllh4Pc;;GG4hll"
        }
      ],
      "is_cutlery": false,
      "is_no_contact_delivery_allowed": true,
      "is_wolt_plus_only": false,
      "lowest_price": null,
      "lowest_price_v2": null,
      "max_quantity_per_purchase": null,
      "min_quantity_per_purchase": null,
      "name": "FRANKO ხელის ბლენდერი FHB-1183 600W შავი/4055544451395",
      "options": [],
      "original_price": null,
      "price": 19900,
      "purchasable_balance": null,
      "restrictions": [],
      "return_policy": null,
      "sell_by_weight_config": null,
      "should_display_purchasable_balance": false,
      "tags": [],
      "unit_info": null,
      "unit_price": null,
      "variant": null
    },
    {
      "id": "67af3b1d0790ca59a0107ad1",
      "advertising_info": null,
      "alcohol_permille": 0,
      "allowed_delivery_methods": [
        "homedelivery",
        "eatin",
        "takeaway"
      ],
      "available_times": [
        {
          "days": [
            1,
            2,
            3,
            4,
            5,
            6,
            7
          ],
          "start_time": 0,
          "end_time": 86400000
        }
      ],
      "barcode_gtin": "4861486223200",
      "caffeine_info": null,
      "can_be_promoted": {
        "basket": true,
        "venue": true,
        "credits": true
      },
      "checksum": "c9cad0a8384a9c5d9406d8e42c95baad",
      "description": "",
      "deposit": null,
      "dietary_preferences": [],
      "disabled_info": null,
      "fulfillment_lead_time": null,
      "has_extra_info": false,
      "images": [
        {
          "url": "https://wolt-menu-images-cdn.wolt.com/menu-images/5eb50a8743ef4f7e46644db9/37b63a2a-ead1-11ef-99ac-d201041e05e4_223578.jpg",
          "blurhash": "j7Z;vTpD;;KXPcGph4pC;;GG4hll"
        }
      ],
      "is_cutlery": false,
      "is_no_contact_delivery_allowed": true,
      "is_wolt_plus_only": false,
      "lowest_price": null,
      "lowest_price_v2": null,
      "max_quantity_per_purchase": null,
      "min_quantity_per_purchase": null,
      "name": "ILITEK სენდვიჩმეიქერი IL5153 750W/4861486223200",
      "options": [],
      "original_price": null,
      "price": 7990,
      "purchasable_balance": null,
      "restrictions": [],
      "return_policy": null,
      "sell_by_weight_config": null,
      "should_display_purchasable_balance": false,
      "tags": [],
      "unit_info": null,
      "unit_price": null,
      "variant": null
    },
    {
      "id": "67af3b22ac95be1f02d7ec46",
      "advertising_info": null,
      "alcohol_permille": 0,
      "allowed_delivery_methods": [
        "homedelivery",
        "eatin",
        "takeaway"
      ],
      "available_times": [
        {
          "days": [
            1,
            2,
            3,
            4,
            5,
            6,
            7
          ],
          "start_time": 0,
          "end_time": 86400000
        }
      ],
      "barcode_gtin": "8004399334182",
      "caffeine_info": null,
      "can_be_promoted": {
        "basket": true,
        "venue": true,
        "credits": true
      },
      "checksum": "fc02b221802b41e81ba04632996e430f",
      "description": "",
      "deposit": null,
      "dietary_preferences": [],
      "disabled_info": null,
      "fulfillment_lead_time": null,
      "has_extra_info": false,
      "images": [
        {
          "url": "https://wolt-menu-images-cdn.wolt.com/menu-images/5eb50a8743ef4f7e46644db9/45393f80-ead1-11ef-a3c1-ae0b03929cb5_302688.jpg",
          "blurhash": "j8ZLrSGG;;CpCpCpGGtT;;tT4hCp"
        }
      ],
      "is_cutlery": false,
      "is_no_contact_delivery_allowed": true,
      "is_wolt_plus_only": false,
      "lowest_price": null,
      "lowest_price_v2": null,
      "max_quantity_per_purchase": null,
      "min_quantity_per_purchase": null,
      "name": "DELONGHI ყავის საფქვავი KG200 შავი/8004399334182",
      "options": [],
      "original_price": null,
      "price": 16900,
      "purchasable_balance": null,
      "restrictions": [],
      "return_policy": null,
      "sell_by_weight_config": null,
      "should_display_purchasable_balance": false,
      "tags": [],
      "unit_info": null,
      "unit_price": null,
      "variant": null
    },
    {
      "id": "67af3b2583422be1b70d3260",
      "advertising_info": null,
      "alcohol_permille": 0,
      "allowed_delivery_methods": [
        "homedelivery",
        "eatin",
        "takeaway"
      ],
      "available_times": [
        {
          "days": [
            1,
            2,
            3,
            4,
            5,
            6,
            7
          ],
          "start_time": 0,
          "end_time": 86400000
        }
      ],
      "barcode_gtin": "2000000057873",
      "caffeine_info": null,
      "can_be_promoted": {
        "basket": true,
        "venue": true,
        "credits": true
      },
      "checksum": "a4939f2cb955216d2b8c5aae0462c1e0",
      "description": "",
      "deposit": null,
      "dietary_preferences": [],
      "disabled_info": null,
      "fulfillment_lead_time": null,
      "has_extra_info": false,
      "images": [
        {
          "url": "https://wolt-menu-images-cdn.wolt.com/menu-images/5eb50a8743ef4f7e46644db9/424a9ed6-ead1-11ef-900b-0e4d2a76e915_291883.jpg",
          "blurhash": "j3:;LXKX;;CGXKGGcPllXKll8yPc"
        }
      ],
      "is_cutlery": false,
      "is_no_contact_delivery_allowed": true,
      "is_wolt_plus_only": false,
      "lowest_price": null,
      "lowest_price_v2": null,
      "max_quantity_per_purchase": null,
      "min_quantity_per_purchase": null,
      "name": "MIDEA მტვერსასრუტი MGE18C BAGLESS 2400W ლურჯი/2000000057873",
      "options": [],
      "original_price": null,
      "price": 29900,
      "purchasable_balance": null,
      "restrictions": [],
      "return_policy": null,
      "sell_by_weight_config": null,
      "should_display_purchasable_balance": false,
      "tags": [],
      "unit_info": null,
      "unit_price": null,
      "variant": null
    },
    {
      "id": "67af3b292e801b8e9da38bc2",
      "advertising_info": null,
      "alcohol_permille": 0,
      "allowed_delivery_methods": [
        "homedelivery",
        "eatin",
        "takeaway"
      ],
      "available_times": [
        {
          "days": [
            1,
            2,
            3,
            4,
            5,
            6,
            7
          ],
          "start_time": 0,
          "end_time": 86400000
        }
      ],
      "barcode_gtin": "123456716803",
      "caffeine_info": null,
      "can_be_promoted": {
        "basket": true,
        "venue": true,
        "credits": true
      },
      "checksum": "63706d02052710099a055a4be52e4306",
      "description": "",
      "deposit": null,
      "dietary_preferences": [],
      "disabled_info": null,
      "fulfillment_lead_time": null,
      "has_extra_info": false,
      "images": [
        {
          "url": "https://wolt-menu-images-cdn.wolt.com/menu-images/5eb50a8743ef4f7e46644db9/31eb90ea-ead1-11ef-8e65-2aa50a22a239_161355.jpg",
          "blurhash": "j3:;LYGp;;KYcPtTTtGG;;GG4hll"
        }
      ],
      "is_cutlery": false,
      "is_no_contact_delivery_allowed": true,
      "is_wolt_plus_only": false,
      "lowest_price": null,
      "lowest_price_v2": null,
      "max_quantity_per_purchase": null,
      "min_quantity_per_purchase": null,
      "name": "ILITEK თმის საშრობი IL6553 1200W/123456716803",
      "options": [],
      "original_price": null,
      "price": 4990,
      "purchasable_balance": null,
      "restrictions": [],
      "return_policy": null,
      "sell_by_weight_config": null,
      "should_display_purchasable_balance": false,
      "tags": [],
      "unit_info": null,
      "unit_price": null,
      "variant": null
    },
    {
      "id": "67af3b2b29d4c5ddae094356",
      "advertising_info": null,
      "alcohol_permille": 0,
      "allowed_delivery_methods": [
        "homedelivery",
        "eatin",
        "takeaway"
      ],
      "available_times": [
        {
          "days": [
            1,
            2,
            3,
            4,
            5,
            6,
            7
          ],
          "start_time": 0,
          "end_time": 86400000
        }
      ],
      "barcode_gtin": "4547201060038",
      "caffeine_info": null,
      "can_be_promoted": {
        "basket": true,
        "venue": true,
        "credits": true
      },
      "checksum": "b4538ee2880f46bcb0276292ee150ad7",
      "description": "",
      "deposit": null,
      "dietary_preferences": [],
      "disabled_info": null,
      "fulfillment_lead_time": null,
      "has_extra_info": false,
      "images": [
        {
          "url": "https://wolt-menu-images-cdn.wolt.com/menu-images/5eb50a8743ef4f7e46644db9/4a8b6a62-ead1-11ef-8237-bed456eec983_337145.jpg",
          "blurhash": "j5:vDVKX;;lkPbKXllh4;;GC8ypH"
        }
      ],
      "is_cutlery": false,
      "is_no_contact_delivery_allowed": true,
      "is_wolt_plus_only": false,
      "lowest_price": null,
      "lowest_price_v2": null,
      "max_quantity_per_purchase": null,
      "min_quantity_per_purchase": null,
      "name": "FUJIFILM ფოტოაპარატი COMBO MINI 12 თეთრი/4547201060038",
      "options": [],
      "original_price": null,
      "price": 44900,
      "purchasable_balance": null,
      "restrictions": [],
      "return_policy": null,
      "sell_by_weight_config": null,
      "should_display_purchasable_balance": false,
      "tags": [],
      "unit_info": null,
      "unit_price": null,
      "variant": null
    },
    {
      "id": "67af3b2ee557160fb188df2c",
      "advertising_info": null,
      "alcohol_permille": 0,
      "allowed_delivery_methods": [
        "homedelivery",
        "eatin",
        "takeaway"
      ],
      "available_times": [
        {
          "days": [
            1,
            2,
            3,
            4,
            5,
            6,
            7
          ],
          "start_time": 0,
          "end_time": 86400000
        }
      ],
      "barcode_gtin": "5553338630012",
      "caffeine_info": null,
      "can_be_promoted": {
        "basket": true,
        "venue": true,
        "credits": true
      },
      "checksum": "99e722eb84854aaa84c963c78f0e09b5",
      "description": "",
      "deposit": null,
      "dietary_preferences": [],
      "disabled_info": null,
      "fulfillment_lead_time": null,
      "has_extra_info": false,
      "images": [
        {
          "url": "https://wolt-menu-images-cdn.wolt.com/menu-images/5eb50a8743ef4f7e46644db9/31b8c142-ead1-11ef-a209-169094648612_153598.jpg",
          "blurhash": "j9Z;rRGF;;GGKWC8lCuo;;Cp8htC"
        }
      ],
      "is_cutlery": false,
      "is_no_contact_delivery_allowed": true,
      "is_wolt_plus_only": false,
      "lowest_price": null,
      "lowest_price_v2": null,
      "max_quantity_per_purchase": null,
      "min_quantity_per_purchase": null,
      "name": "FRANKO ჩირის აპარატი FDH-1065 /5553338630012",
      "options": [],
      "original_price": null,
      "price": 21900,
      "purchasable_balance": null,
      "restrictions": [],
      "return_policy": null,
      "sell_by_weight_config": null,
      "should_display_purchasable_balance": false,
      "tags": [],
      "unit_info": null,
      "unit_price": null,
      "variant": null
    },
    {
      "id": "67af3b302992138af694f41c",
      "advertising_info": null,
      "alcohol_permille": 0,
      "allowed_delivery_methods": [
        "homedelivery",
        "eatin",
        "takeaway"
      ],
      "available_times": [
        {
          "days": [
            1,
            2,
            3,
            4,
            5,
            6,
            7
          ],
          "start_time": 0,
          "end_time": 86400000
        }
      ],
      "barcode_gtin": "4065544152659",
      "caffeine_info": null,
      "can_be_promoted": {
        "basket": true,
        "venue": true,
        "credits": true
      },
      "checksum": "62cb74c0dc518e2036e457d55abebff7",
      "description": "",
      "deposit": null,
      "dietary_preferences": [],
      "disabled_info": null,
      "fulfillment_lead_time": null,
      "has_extra_info": false,
      "images": [
        {
          "url": "https://wolt-menu-images-cdn.wolt.com/menu-images/5eb50a8743ef4f7e46644db9/503a829a-ead1-11ef-85c4-8e166704955d_351851.jpg",
          "blurhash": "j3:;LXKX;;pCllGGKXll;;pC4iKY"
        }
      ],
      "is_cutlery": false,
      "is_no_contact_delivery_allowed": true,
      "is_wolt_plus_only": false,
      "lowest_price": null,
      "lowest_price_v2": null,
      "max_quantity_per_purchase": null,
      "min_quantity_per_purchase": null,
      "name": "FRANKO თმის საშრობი FHD-1237/4065544152659",
      "options": [],
      "original_price": null,
      "price": 19900,
      "purchasable_balance": null,
      "restrictions": [],
      "return_policy": null,
      "sell_by_weight_config": null,
      "should_display_purchasable_balance": false,
      "tags": [],
      "unit_info": null,
      "unit_price": null,
      "variant": null
    },
    {
      "id": "67af3b3476d7a9adb4982ee2",
      "advertising_info": null,
      "alcohol_permille": 0,
      "allowed_delivery_methods": [
        "homedelivery",
        "eatin",
        "takeaway"
      ],
      "available_times": [
        {
          "days": [
            1,
            2,
            3,
            4,
            5,
            6,
            7
          ],
          "start_time": 0,
          "end_time": 86400000
        }
      ],
      "barcode_gtin": "4065544151850",
      "caffeine_info": null,
      "can_be_promoted": {
        "basket": true,
        "venue": true,
        "credits": true
      },
      "checksum": "046d133a27c989f162694a9c0849455e",
      "description": "",
      "deposit": null,
      "dietary_preferences": [],
      "disabled_info": null,
      "fulfillment_lead_time": null,
      "has_extra_info": false,
      "images": [
        {
          "url": "https://wolt-menu-images-cdn.wolt.com/menu-images/5eb50a8743ef4f7e46644db9/3e529fae-ead1-11ef-a997-2655e86c8b3c_273453.jpg",
          "blurhash": "j2;fTZKX;;llTtpCh4KX;KpC4yKX"
        }
      ],
      "is_cutlery": false,
      "is_no_contact_delivery_allowed": true,
      "is_wolt_plus_only": false,
      "lowest_price": null,
      "lowest_price_v2": null,
      "max_quantity_per_purchase": null,
      "min_quantity_per_purchase": null,
      "name": "FRANKO ორთქლის უთო FHS-1199/4065544151850",
      "options": [],
      "original_price": null,
      "price": 9900,
      "purchasable_balance": null,
      "restrictions": [],
      "return_policy": null,
      "sell_by_weight_config": null,
      "should_display_purchasable_balance": false,
      "tags": [],
      "unit_info": null,
      "unit_price": null,
      "variant": null
    },
    {
      "id": "67af3b375ae06b2da22ef91b",
      "advertising_info": null,
      "alcohol_permille": 0,
      "allowed_delivery_methods": [
        "homedelivery",
        "eatin",
        "takeaway"
      ],
      "available_times": [
        {
          "days": [
            1,
            2,
            3,
            4,
            5,
            6,
            7
          ],
          "start_time": 0,
          "end_time": 86400000
        }
      ],
      "barcode_gtin": "6954368866867",
      "caffeine_info": null,
      "can_be_promoted": {
        "basket": true,
        "venue": true,
        "credits": true
      },
      "checksum": "5eb77a723be70d06321e8699ee213c19",
      "description": "",
      "deposit": null,
      "dietary_preferences": [],
      "disabled_info": null,
      "fulfillment_lead_time": null,
      "has_extra_info": false,
      "images": [
        {
          "url": "https://wolt-menu-images-cdn.wolt.com/menu-images/5eb50a8743ef4f7e46644db9/4aa30276-ead1-11ef-a383-1a7241bde26b_337184.jpg",
          "blurhash": "j2;fPYll;;TtPcllllPc;;KX4hh4"
        }
      ],
      "is_cutlery": false,
      "is_no_contact_delivery_allowed": true,
      "is_wolt_plus_only": false,
      "lowest_price": null,
      "lowest_price_v2": null,
      "max_quantity_per_purchase": null,
      "min_quantity_per_purchase": null,
      "name": "SOLLEX ხორცსაკეპი SL625 2600W/6954368866867",
      "options": [],
      "original_price": null,
      "price": 16900,
      "purchasable_balance": null,
      "restrictions": [],
      "return_policy": null,
      "sell_by_weight_config": null,
      "should_display_purchasable_balance": false,
      "tags": [],
      "unit_info": null,
      "unit_price": null,
      "variant": null
    },
    {
      "id": "67af3b398907ebb6f4216e2d",
      "advertising_info": null,
      "alcohol_permille": 0,
      "allowed_delivery_methods": [
        "homedelivery",
        "eatin",
        "takeaway"
      ],
      "available_times": [
        {
          "days": [
            1,
            2,
            3,
            4,
            5,
            6,
            7
          ],
          "start_time": 0,
          "end_time": 86400000
        }
      ],
      "barcode_gtin": "4065544451479",
      "caffeine_info": null,
      "can_be_promoted": {
        "basket": true,
        "venue": true,
        "credits": true
      },
      "checksum": "183796b06f7d37ab9f8f464f3a253164",
      "description": "",
      "deposit": null,
      "dietary_preferences": [],
      "disabled_info": null,
      "fulfillment_lead_time": null,
      "has_extra_info": false,
      "images": [
        {
          "url": "https://wolt-menu-images-cdn.wolt.com/menu-images/5eb50a8743ef4f7e46644db9/3e6c21b8-ead1-11ef-9c04-dacba37cae33_277988.jpg",
          "blurhash": "j8ZLvTGG;;pCPcKXh4h4;;ll4hPb"
        }
      ],
      "is_cutlery": false,
      "is_no_contact_delivery_allowed": true,
      "is_wolt_plus_only": false,
      "lowest_price": null,
      "lowest_price_v2": null,
      "max_quantity_per_purchase": null,
      "min_quantity_per_purchase": null,
      "name": "FRANKO უთო FSI-1189 2600W /4065544451479",
      "options": [],
      "original_price": null,
      "price": 8990,
      "purchasable_balance": null,
      "restrictions": [],
      "return_policy": null,
      "sell_by_weight_config": null,
      "should_display_purchasable_balance": false,
      "tags": [],
      "unit_info": null,
      "unit_price": null,
      "variant": null
    },
    {
      "id": "67af3b3cac95be1f02d7ec4e",
      "advertising_info": null,
      "alcohol_permille": 0,
      "allowed_delivery_methods": [
        "homedelivery",
        "eatin",
        "takeaway"
      ],
      "available_times": [
        {
          "days": [
            1,
            2,
            3,
            4,
            5,
            6,
            7
          ],
          "start_time": 0,
          "end_time": 86400000
        }
      ],
      "barcode_gtin": "2018072720106",
      "caffeine_info": null,
      "can_be_promoted": {
        "basket": true,
        "venue": true,
        "credits": true
      },
      "checksum": "c8ae5c9744ef08c74a8498f29b55b005",
      "description": "",
      "deposit": null,
      "dietary_preferences": [],
      "disabled_info": null,
      "fulfillment_lead_time": null,
      "has_extra_info": false,
      "images": [
        {
          "url": "https://wolt-menu-images-cdn.wolt.com/menu-images/5eb50a8743ef4f7e46644db9/37af467a-ead1-11ef-adb0-12ab05747dad_241122.jpg",
          "blurhash": "j5:vDWKW;;pCTcGGh4ll;;pC0hKX"
        }
      ],
      "is_cutlery": false,
      "is_no_contact_delivery_allowed": true,
      "is_wolt_plus_only": false,
      "lowest_price": null,
      "lowest_price_v2": null,
      "max_quantity_per_purchase": null,
      "min_quantity_per_purchase": null,
      "name": "ILITEK უთო IL2010 2200W/2018072720106",
      "options": [],
      "original_price": null,
      "price": 4990,
      "purchasable_balance": null,
      "restrictions": [],
      "return_policy": null,
      "sell_by_weight_config": null,
      "should_display_purchasable_balance": false,
      "tags": [],
      "unit_info": null,
      "unit_price": null,
      "variant": null
    },
    {
      "id": "67af3b3e1fa00330fdc28652",
      "advertising_info": null,
      "alcohol_permille": 0,
      "allowed_delivery_methods": [
        "homedelivery",
        "eatin",
        "takeaway"
      ],
      "available_times": [
        {
          "days": [
            1,
            2,
            3,
            4,
            5,
            6,
            7
          ],
          "start_time": 0,
          "end_time": 86400000
        }
      ],
      "barcode_gtin": "4065544152765",
      "caffeine_info": null,
      "can_be_promoted": {
        "basket": true,
        "venue": true,
        "credits": true
      },
      "checksum": "ab8047e817a25358ca14c720abfc2b32",
      "description": "",
      "deposit": null,
      "dietary_preferences": [],
      "disabled_info": null,
      "fulfillment_lead_time": null,
      "has_extra_info": false,
      "images": [
        {
          "url": "https://wolt-menu-images-cdn.wolt.com/menu-images/5eb50a8743ef4f7e46644db9/4dc2029a-ead1-11ef-aee1-860a16ce2a4d_341912.jpg",
          "blurhash": "j7Z;vTCp;;KXKXGGpCll;;Cp4htT"
        }
      ],
      "is_cutlery": false,
      "is_no_contact_delivery_allowed": true,
      "is_wolt_plus_only": false,
      "lowest_price": null,
      "lowest_price_v2": null,
      "max_quantity_per_purchase": null,
      "min_quantity_per_purchase": null,
      "name": "FRANKO CAPSULE ყავის აპარატი FCM-1240/4065544152765",
      "options": [],
      "original_price": null,
      "price": 29900,
      "purchasable_balance": null,
      "restrictions": [],
      "return_policy": null,
      "sell_by_weight_config": null,
      "should_display_purchasable_balance": false,
      "tags": [],
      "unit_info": null,
      "unit_price": null,
      "variant": null
    },
    {
      "id": "67af3b403cbb74d2141ee20c",
      "advertising_info": null,
      "alcohol_permille": 0,
      "allowed_delivery_methods": [
        "homedelivery",
        "eatin",
        "takeaway"
      ],
      "available_times": [
        {
          "days": [
            1,
            2,
            3,
            4,
            5,
            6,
            7
          ],
          "start_time": 0,
          "end_time": 86400000
        }
      ],
      "barcode_gtin": "4065544151706",
      "caffeine_info": null,
      "can_be_promoted": {
        "basket": true,
        "venue": true,
        "credits": true
      },
      "checksum": "a866f57f2fc33b83d757220d8b5dd6f6",
      "description": "",
      "deposit": null,
      "dietary_preferences": [],
      "disabled_info": null,
      "fulfillment_lead_time": null,
      "has_extra_info": false,
      "images": [
        {
          "url": "https://wolt-menu-images-cdn.wolt.com/menu-images/5eb50a8743ef4f7e46644db9/424a9f12-ead1-11ef-8adb-12ab05747dad_296886.jpg",
          "blurhash": "j6:vDVtT;;KXPcCph4tT;;GG4hpC"
        }
      ],
      "is_cutlery": false,
      "is_no_contact_delivery_allowed": true,
      "is_wolt_plus_only": false,
      "lowest_price": null,
      "lowest_price_v2": null,
      "max_quantity_per_purchase": null,
      "min_quantity_per_purchase": null,
      "name": "FRANKO ჩოფერი FCH-1202 500ვ შავი/4065544151706",
      "options": [],
      "original_price": null,
      "price": 11900,
      "purchasable_balance": null,
      "restrictions": [],
      "return_policy": null,
      "sell_by_weight_config": null,
      "should_display_purchasable_balance": false,
      "tags": [],
      "unit_info": null,
      "unit_price": null,
      "variant": null
    },
    {
      "id": "67af3b433aec4e5a3e0b339e",
      "advertising_info": null,
      "alcohol_permille": 0,
      "allowed_delivery_methods": [
        "homedelivery",
        "eatin",
        "takeaway"
      ],
      "available_times": [
        {
          "days": [
            1,
            2,
            3,
            4,
            5,
            6,
            7
          ],
          "start_time": 0,
          "end_time": 86400000
        }
      ],
      "barcode_gtin": "2900000066335",
      "caffeine_info": null,
      "can_be_promoted": {
        "basket": true,
        "venue": true,
        "credits": true
      },
      "checksum": "3ce24f8459145b90872194f374bdbe18",
      "description": "",
      "deposit": null,
      "dietary_preferences": [],
      "disabled_info": null,
      "fulfillment_lead_time": null,
      "has_extra_info": false,
      "images": [
        {
          "url": "https://wolt-menu-images-cdn.wolt.com/menu-images/5eb50a8743ef4f7e46644db9/45396154-ead1-11ef-81fc-6a7353e68ad9_315098.jpg",
          "blurhash": "j3:;LXKX;;GGPctTllGG;;tT4hGG"
        }
      ],
      "is_cutlery": false,
      "is_no_contact_delivery_allowed": true,
      "is_wolt_plus_only": false,
      "lowest_price": null,
      "lowest_price_v2": null,
      "max_quantity_per_purchase": null,
      "min_quantity_per_purchase": null,
      "name": "MIDEA ტოსტერი MT-RS2L17W2SS 950W/2900000066335",
      "options": [],
      "original_price": null,
      "price": 8900,
      "purchasable_balance": null,
      "restrictions": [],
      "return_policy": null,
      "sell_by_weight_config": null,
      "should_display_purchasable_balance": false,
      "tags": [],
      "unit_info": null,
      "unit_price": null,
      "variant": null
    },
    {
      "id": "67af3b46ee76f294b9eae878",
      "advertising_info": null,
      "alcohol_permille": 0,
      "allowed_delivery_methods": [
        "homedelivery",
        "eatin",
        "takeaway"
      ],
      "available_times": [
        {
          "days": [
            1,
            2,
            3,
            4,
            5,
            6,
            7
          ],
          "start_time": 0,
          "end_time": 86400000
        }
      ],
      "barcode_gtin": "2000000054117",
      "caffeine_info": null,
      "can_be_promoted": {
        "basket": true,
        "venue": true,
        "credits": true
      },
      "checksum": "39bfd3f866ebe6d0bd33c6049b021644",
      "description": "",
      "deposit": null,
      "dietary_preferences": [],
      "disabled_info": null,
      "fulfillment_lead_time": null,
      "has_extra_info": false,
      "images": [
        {
          "url": "https://wolt-menu-images-cdn.wolt.com/menu-images/5eb50a8743ef4f7e46644db9/3e53e9d6-ead1-11ef-a51b-263763f20541_278440.jpg",
          "blurhash": "j3:;LXGG;;KXTtCph4pC;;Cp8ypC"
        }
      ],
      "is_cutlery": false,
      "is_no_contact_delivery_allowed": true,
      "is_wolt_plus_only": false,
      "lowest_price": null,
      "lowest_price_v2": null,
      "max_quantity_per_purchase": null,
      "min_quantity_per_purchase": null,
      "name": "MIDEA ბლენდერი BL2516A 600ვ შავი/2000000054117",
      "options": [],
      "original_price": null,
      "price": 13900,
      "purchasable_balance": null,
      "restrictions": [],
      "return_policy": null,
      "sell_by_weight_config": null,
      "should_display_purchasable_balance": false,
      "tags": [],
      "unit_info": null,
      "unit_price": null,
      "variant": null
    },
    {
      "id": "67af3b48b66519af3cecf91f",
      "advertising_info": null,
      "alcohol_permille": 0,
      "allowed_delivery_methods": [
        "homedelivery",
        "eatin",
        "takeaway"
      ],
      "available_times": [
        {
          "days": [
            1,
            2,
            3,
            4,
            5,
            6,
            7
          ],
          "start_time": 0,
          "end_time": 86400000
        }
      ],
      "barcode_gtin": "740617332742",
      "caffeine_info": null,
      "can_be_promoted": {
        "basket": true,
        "venue": true,
        "credits": true
      },
      "checksum": "b182746275ef8715967258b23f4a20e1",
      "description": "",
      "deposit": null,
      "dietary_preferences": [],
      "disabled_info": null,
      "fulfillment_lead_time": null,
      "has_extra_info": false,
      "images": [
        {
          "url": "https://wolt-menu-images-cdn.wolt.com/menu-images/5eb50a8743ef4f7e46644db9/4a88e4e0-ead1-11ef-904b-82a46f1b4864_338744.jpg",
          "blurhash": "j5:vDVGG;;GGKXy9tTtT;;Cn00pV"
        }
      ],
      "is_cutlery": false,
      "is_no_contact_delivery_allowed": true,
      "is_wolt_plus_only": false,
      "lowest_price": null,
      "lowest_price_v2": null,
      "max_quantity_per_purchase": null,
      "min_quantity_per_purchase": null,
      "name": "Kingston ფლეშკა DR DTXON/128გბ/740617332742",
      "options": [],
      "original_price": null,
      "price": 4900,
      "purchasable_balance": null,
      "restrictions": [],
      "return_policy": null,
      "sell_by_weight_config": null,
      "should_display_purchasable_balance": false,
      "tags": [],
      "unit_info": null,
      "unit_price": null,
      "variant": null
    },
    {
      "id": "67af3b4ad66b41a7bdfd3b89",
      "advertising_info": null,
      "alcohol_permille": 0,
      "allowed_delivery_methods": [
        "homedelivery",
        "eatin",
        "takeaway"
      ],
      "available_times": [
        {
          "days": [
            1,
            2,
            3,
            4,
            5,
            6,
            7
          ],
          "start_time": 0,
          "end_time": 86400000
        }
      ],
      "barcode_gtin": "6944271673454",
      "caffeine_info": null,
      "can_be_promoted": {
        "basket": true,
        "venue": true,
        "credits": true
      },
      "checksum": "c206fbb9b074628faaf342a370ca7102",
      "description": "",
      "deposit": null,
      "dietary_preferences": [],
      "disabled_info": null,
      "fulfillment_lead_time": null,
      "has_extra_info": false,
      "images": [
        {
          "url": "https://wolt-menu-images-cdn.wolt.com/menu-images/5eb50a8743ef4f7e46644db9/4da757ce-ead1-11ef-8bc1-f277f9bf0e6e_341911.jpg",
          "blurhash": "j9ZfjQCp;;GGGGtTGGCp;;Cp00pC"
        }
      ],
      "is_cutlery": false,
      "is_no_contact_delivery_allowed": true,
      "is_wolt_plus_only": false,
      "lowest_price": null,
      "lowest_price_v2": null,
      "max_quantity_per_purchase": null,
      "min_quantity_per_purchase": null,
      "name": "MIDEA მიკროტალღური AM823A2AT-B 23ლ/6944271673454",
      "options": [],
      "original_price": null,
      "price": 26900,
      "purchasable_balance": null,
      "restrictions": [],
      "return_policy": null,
      "sell_by_weight_config": null,
      "should_display_purchasable_balance": false,
      "tags": [],
      "unit_info": null,
      "unit_price": null,
      "variant": null
    },
    {
      "id": "67af3b4c44617e6cbfdf8b53",
      "advertising_info": null,
      "alcohol_permille": 0,
      "allowed_delivery_methods": [
        "homedelivery",
        "eatin",
        "takeaway"
      ],
      "available_times": [
        {
          "days": [
            1,
            2,
            3,
            4,
            5,
            6,
            7
          ],
          "start_time": 0,
          "end_time": 86400000
        }
      ],
      "barcode_gtin": "4055555578876",
      "caffeine_info": null,
      "can_be_promoted": {
        "basket": true,
        "venue": true,
        "credits": true
      },
      "checksum": "dc55a52ae32984b1d4f22597be288ee2",
      "description": "",
      "deposit": null,
      "dietary_preferences": [],
      "disabled_info": null,
      "fulfillment_lead_time": null,
      "has_extra_info": false,
      "images": [
        {
          "url": "https://wolt-menu-images-cdn.wolt.com/menu-images/5eb50a8743ef4f7e46644db9/34ee037c-ead1-11ef-a1e2-eab9f01fb128_200921.jpg",
          "blurhash": "j5:vDVPc;;h4pCGGKXll;;ll4hPc"
        }
      ],
      "is_cutlery": false,
      "is_no_contact_delivery_allowed": true,
      "is_wolt_plus_only": false,
      "lowest_price": null,
      "lowest_price_v2": null,
      "max_quantity_per_purchase": null,
      "min_quantity_per_purchase": null,
      "name": "FRANKO ფრის აპარატი 2.5L FDF-1133/4055555578876",
      "options": [],
      "original_price": null,
      "price": 19900,
      "purchasable_balance": null,
      "restrictions": [],
      "return_policy": null,
      "sell_by_weight_config": null,
      "should_display_purchasable_balance": false,
      "tags": [],
      "unit_info": null,
      "unit_price": null,
      "variant": null
    },
    {
      "id": "67af3b4f5033f1fa485c66af",
      "advertising_info": null,
      "alcohol_permille": 0,
      "allowed_delivery_methods": [
        "homedelivery",
        "eatin",
        "takeaway"
      ],
      "available_times": [
        {
          "days": [
            1,
            2,
            3,
            4,
            5,
            6,
            7
          ],
          "start_time": 0,
          "end_time": 86400000
        }
      ],
      "barcode_gtin": "4055544444472",
      "caffeine_info": null,
      "can_be_promoted": {
        "basket": true,
        "venue": true,
        "credits": true
      },
      "checksum": "caaf60a729d929124243892d9a76d720",
      "description": "",
      "deposit": null,
      "dietary_preferences": [],
      "disabled_info": null,
      "fulfillment_lead_time": null,
      "has_extra_info": false,
      "images": [
        {
          "url": "https://wolt-menu-images-cdn.wolt.com/menu-images/5eb50a8743ef4f7e46644db9/3a82ffd6-ead1-11ef-adb0-12ab05747dad_258650.jpg",
          "blurhash": "j4:LHWGG;;KXPcllh4PcXKtT8yGG"
        }
      ],
      "is_cutlery": false,
      "is_no_contact_delivery_allowed": true,
      "is_wolt_plus_only": false,
      "lowest_price": null,
      "lowest_price_v2": null,
      "max_quantity_per_purchase": null,
      "min_quantity_per_purchase": null,
      "name": "FRANKO ხელის ბლენდერი FHB-1122 500W/4055544444472",
      "options": [],
      "original_price": null,
      "price": 11900,
      "purchasable_balance": null,
      "restrictions": [],
      "return_policy": null,
      "sell_by_weight_config": null,
      "should_display_purchasable_balance": false,
      "tags": [],
      "unit_info": null,
      "unit_price": null,
      "variant": null
    },
    {
      "id": "67af3b5260b3805a2bdf5b9b",
      "advertising_info": null,
      "alcohol_permille": 0,
      "allowed_delivery_methods": [
        "homedelivery",
        "eatin",
        "takeaway"
      ],
      "available_times": [
        {
          "days": [
            1,
            2,
            3,
            4,
            5,
            6,
            7
          ],
          "start_time": 0,
          "end_time": 86400000
        }
      ],
      "barcode_gtin": "740617309829",
      "caffeine_info": null,
      "can_be_promoted": {
        "basket": true,
        "venue": true,
        "credits": true
      },
      "checksum": "dfeca7dd108ddf5399fe484da7f97bea",
      "description": "",
      "deposit": null,
      "dietary_preferences": [],
      "disabled_info": null,
      "fulfillment_lead_time": null,
      "has_extra_info": false,
      "images": [
        {
          "url": "https://wolt-menu-images-cdn.wolt.com/menu-images/5eb50a8743ef4f7e46644db9/3a6a1c50-ead1-11ef-9b4b-9a5d917a3b19_246194.jpg",
          "blurhash": "j4:LHWll;;PtKXy8Cpy8;;KX00h4"
        }
      ],
      "is_cutlery": false,
      "is_no_contact_delivery_allowed": true,
      "is_wolt_plus_only": false,
      "lowest_price": null,
      "lowest_price_v2": null,
      "max_quantity_per_purchase": null,
      "min_quantity_per_purchase": null,
      "name": "KINGSTON 64GB EXODIA 3.2 USB/740617309829",
      "options": [],
      "original_price": null,
      "price": 2995,
      "purchasable_balance": null,
      "restrictions": [],
      "return_policy": null,
      "sell_by_weight_config": null,
      "should_display_purchasable_balance": false,
      "tags": [],
      "unit_info": null,
      "unit_price": null,
      "variant": null
    },
    {
      "id": "67af3b5663e91c5686568b95",
      "advertising_info": null,
      "alcohol_permille": 0,
      "allowed_delivery_methods": [
        "homedelivery",
        "eatin",
        "takeaway"
      ],
      "available_times": [
        {
          "days": [
            1,
            2,
            3,
            4,
            5,
            6,
            7
          ],
          "start_time": 0,
          "end_time": 86400000
        }
      ],
      "barcode_gtin": "5011423003542",
      "caffeine_info": null,
      "can_be_promoted": {
        "basket": true,
        "venue": true,
        "credits": true
      },
      "checksum": "82f39b1dce11a8a2d466f1030c897759",
      "description": "",
      "deposit": null,
      "dietary_preferences": [],
      "disabled_info": null,
      "fulfillment_lead_time": null,
      "has_extra_info": false,
      "images": [
        {
          "url": "https://wolt-menu-images-cdn.wolt.com/menu-images/5eb50a8743ef4f7e46644db9/50204722-ead1-11ef-8a0f-82a46f1b4864_351870.jpg",
          "blurhash": "j5:LHWGG;;GGPcCph4tT;;Cp8htT"
        }
      ],
      "is_cutlery": false,
      "is_no_contact_delivery_allowed": true,
      "is_wolt_plus_only": false,
      "lowest_price": null,
      "lowest_price_v2": null,
      "max_quantity_per_purchase": null,
      "min_quantity_per_purchase": null,
      "name": "KENWOOD ჩოფერი CH61.100WH 500W/5011423003542",
      "options": [],
      "original_price": null,
      "price": 11900,
      "purchasable_balance": null,
      "restrictions": [],
      "return_policy": null,
      "sell_by_weight_config": null,
      "should_display_purchasable_balance": false,
      "tags": [],
      "unit_info": null,
      "unit_price": null,
      "variant": null
    },
    {
      "id": "67af3b5a93af4d034f071150",
      "advertising_info": null,
      "alcohol_permille": 0,
      "allowed_delivery_methods": [
        "homedelivery",
        "eatin",
        "takeaway"
      ],
      "available_times": [
        {
          "days": [
            1,
            2,
            3,
            4,
            5,
            6,
            7
          ],
          "start_time": 0,
          "end_time": 86400000
        }
      ],
      "barcode_gtin": "8610256565554",
      "caffeine_info": null,
      "can_be_promoted": {
        "basket": true,
        "venue": true,
        "credits": true
      },
      "checksum": "c94abf12bc26877acaa7e528eba45ae8",
      "description": "",
      "deposit": null,
      "dietary_preferences": [],
      "disabled_info": null,
      "fulfillment_lead_time": null,
      "has_extra_info": false,
      "images": [
        {
          "url": "https://wolt-menu-images-cdn.wolt.com/menu-images/5eb50a8743ef4f7e46644db9/31d32172-ead1-11ef-9675-2aa50a22a239_146231.jpg",
          "blurhash": "j7:fzUKX;;llPcCph4pC;;pC4hKX"
        }
      ],
      "is_cutlery": false,
      "is_no_contact_delivery_allowed": true,
      "is_wolt_plus_only": false,
      "lowest_price": null,
      "lowest_price_v2": null,
      "max_quantity_per_purchase": null,
      "min_quantity_per_purchase": null,
      "name": "FRANKO მიქსერი FMX-1009 450W BLK/8610256565554",
      "options": [],
      "original_price": null,
      "price": 13900,
      "purchasable_balance": null,
      "restrictions": [],
      "return_policy": null,
      "sell_by_weight_config": null,
      "should_display_purchasable_balance": false,
      "tags": [],
      "unit_info": null,
      "unit_price": null,
      "variant": null
    },
    {
      "id": "67af3b5c44985dd211e9654d",
      "advertising_info": null,
      "alcohol_permille": 0,
      "allowed_delivery_methods": [
        "homedelivery",
        "eatin",
        "takeaway"
      ],
      "available_times": [
        {
          "days": [
            1,
            2,
            3,
            4,
            5,
            6,
            7
          ],
          "start_time": 0,
          "end_time": 86400000
        }
      ],
      "barcode_gtin": "6941991101540",
      "caffeine_info": null,
      "can_be_promoted": {
        "basket": true,
        "venue": true,
        "credits": true
      },
      "checksum": "9881579a58a3d0780aeefdbd72047c67",
      "description": "",
      "deposit": null,
      "dietary_preferences": [],
      "disabled_info": null,
      "fulfillment_lead_time": null,
      "has_extra_info": false,
      "images": [
        {
          "url": "https://wolt-menu-images-cdn.wolt.com/menu-images/5eb50a8743ef4f7e46644db9/52dd875e-ead1-11ef-91d5-4ac7f11f6864_357461.jpg",
          "blurhash": "j8:vnRF4;;HtlDGGKGll;;uX8hAQ"
        }
      ],
      "is_cutlery": false,
      "is_no_contact_delivery_allowed": true,
      "is_wolt_plus_only": false,
      "lowest_price": null,
      "lowest_price_v2": null,
      "max_quantity_per_purchase": null,
      "min_quantity_per_purchase": null,
      "name": "HOCO გადამყვანი ISTAG V1/6941991101540",
      "options": [],
      "original_price": null,
      "price": 2900,
      "purchasable_balance": null,
      "restrictions": [],
      "return_policy": null,
      "sell_by_weight_config": null,
      "should_display_purchasable_balance": false,
      "tags": [],
      "unit_info": null,
      "unit_price": null,
      "variant": null
    },
    {
      "id": "67af3b5fdfb8da44546c67ee",
      "advertising_info": null,
      "alcohol_permille": 0,
      "allowed_delivery_methods": [
        "homedelivery",
        "eatin",
        "takeaway"
      ],
      "available_times": [
        {
          "days": [
            1,
            2,
            3,
            4,
            5,
            6,
            7
          ],
          "start_time": 0,
          "end_time": 86400000
        }
      ],
      "barcode_gtin": "2000000021881",
      "caffeine_info": null,
      "can_be_promoted": {
        "basket": true,
        "venue": true,
        "credits": true
      },
      "checksum": "c209c0d7143cdc68dd8d170a70670f94",
      "description": "",
      "deposit": null,
      "dietary_preferences": [],
      "disabled_info": null,
      "fulfillment_lead_time": null,
      "has_extra_info": false,
      "images": [
        {
          "url": "https://wolt-menu-images-cdn.wolt.com/menu-images/5eb50a8743ef4f7e46644db9/3e7d4e48-ead1-11ef-9a80-a684904cd39b_278442.jpg",
          "blurhash": "j4:LHWGG;;GGcPGGTtpC;;tT4hCp"
        }
      ],
      "is_cutlery": false,
      "is_no_contact_delivery_allowed": true,
      "is_wolt_plus_only": false,
      "lowest_price": null,
      "lowest_price_v2": null,
      "max_quantity_per_purchase": null,
      "min_quantity_per_purchase": null,
      "name": "MIDEA მიქსერი HM0293 300ვ BLK/2000000021881",
      "options": [],
      "original_price": null,
      "price": 7900,
      "purchasable_balance": null,
      "restrictions": [],
      "return_policy": null,
      "sell_by_weight_config": null,
      "should_display_purchasable_balance": false,
      "tags": [],
      "unit_info": null,
      "unit_price": null,
      "variant": null
    },
    {
      "id": "67af3b620fe4403d6581b70a",
      "advertising_info": null,
      "alcohol_permille": 0,
      "allowed_delivery_methods": [
        "homedelivery",
        "eatin",
        "takeaway"
      ],
      "available_times": [
        {
          "days": [
            1,
            2,
            3,
            4,
            5,
            6,
            7
          ],
          "start_time": 0,
          "end_time": 86400000
        }
      ],
      "barcode_gtin": "4065544152338",
      "caffeine_info": null,
      "can_be_promoted": {
        "basket": true,
        "venue": true,
        "credits": true
      },
      "checksum": "01402aee1e19960b60a981850100a0d4",
      "description": "",
      "deposit": null,
      "dietary_preferences": [],
      "disabled_info": null,
      "fulfillment_lead_time": null,
      "has_extra_info": false,
      "images": [
        {
          "url": "https://wolt-menu-images-cdn.wolt.com/menu-images/5eb50a8743ef4f7e46644db9/47e08a86-ead1-11ef-a985-8e43fbea51da_334292.jpg",
          "blurhash": "j9ZvnRGG;;GGKXpCpCGG;;Cp4htT"
        }
      ],
      "is_cutlery": false,
      "is_no_contact_delivery_allowed": true,
      "is_wolt_plus_only": false,
      "lowest_price": null,
      "lowest_price_v2": null,
      "max_quantity_per_purchase": null,
      "min_quantity_per_purchase": null,
      "name": "FRANKO ტოსტერი FTS-1221 800W შავი/4065544152338",
      "options": [],
      "original_price": null,
      "price": 7490,
      "purchasable_balance": null,
      "restrictions": [],
      "return_policy": null,
      "sell_by_weight_config": null,
      "should_display_purchasable_balance": false,
      "tags": [],
      "unit_info": null,
      "unit_price": null,
      "variant": null
    },
    {
      "id": "67af3b6693af4d034f07115f",
      "advertising_info": null,
      "alcohol_permille": 0,
      "allowed_delivery_methods": [
        "homedelivery",
        "eatin",
        "takeaway"
      ],
      "available_times": [
        {
          "days": [
            1,
            2,
            3,
            4,
            5,
            6,
            7
          ],
          "start_time": 0,
          "end_time": 86400000
        }
      ],
      "barcode_gtin": "4055555550209",
      "caffeine_info": null,
      "can_be_promoted": {
        "basket": true,
        "venue": true,
        "credits": true
      },
      "checksum": "70cb2d6454b15fcf19e6911eb40dd1a0",
      "description": "",
      "deposit": null,
      "dietary_preferences": [],
      "disabled_info": null,
      "fulfillment_lead_time": null,
      "has_extra_info": false,
      "images": [
        {
          "url": "https://wolt-menu-images-cdn.wolt.com/menu-images/5eb50a8743ef4f7e46644db9/31db2ab6-ead1-11ef-8265-6260eab0611a_159790.jpg",
          "blurhash": "j5:vDVpC;;PcKXCpllpC;;KX00ll"
        }
      ],
      "is_cutlery": false,
      "is_no_contact_delivery_allowed": true,
      "is_wolt_plus_only": false,
      "lowest_price": null,
      "lowest_price_v2": null,
      "max_quantity_per_purchase": null,
      "min_quantity_per_purchase": null,
      "name": "FRANKO სენდვიჩმეიქერი FSM-1095 700W/4055555550209",
      "options": [],
      "original_price": null,
      "price": 7990,
      "purchasable_balance": null,
      "restrictions": [],
      "return_policy": null,
      "sell_by_weight_config": null,
      "should_display_purchasable_balance": false,
      "tags": [],
      "unit_info": null,
      "unit_price": null,
      "variant": null
    },
    {
      "id": "67af3b6a0fe4403d6581b715",
      "advertising_info": null,
      "alcohol_permille": 0,
      "allowed_delivery_methods": [
        "homedelivery",
        "eatin",
        "takeaway"
      ],
      "available_times": [
        {
          "days": [
            1,
            2,
            3,
            4,
            5,
            6,
            7
          ],
          "start_time": 0,
          "end_time": 86400000
        }
      ],
      "barcode_gtin": "4065544152826",
      "caffeine_info": null,
      "can_be_promoted": {
        "basket": true,
        "venue": true,
        "credits": true
      },
      "checksum": "9bd0e8483a1f5bae5ea2a6409c6b8493",
      "description": "",
      "deposit": null,
      "dietary_preferences": [],
      "disabled_info": null,
      "fulfillment_lead_time": null,
      "has_extra_info": false,
      "images": [
        {
          "url": "https://wolt-menu-images-cdn.wolt.com/menu-images/5eb50a8743ef4f7e46644db9/4da77010-ead1-11ef-937c-d2432758f71d_351596.jpg",
          "blurhash": "j2;fPYPc;;h4KXtTtCGG;;ll4hPc"
        }
      ],
      "is_cutlery": false,
      "is_no_contact_delivery_allowed": true,
      "is_wolt_plus_only": false,
      "lowest_price": null,
      "lowest_price_v2": null,
      "max_quantity_per_purchase": null,
      "min_quantity_per_purchase": null,
      "name": "FRANKO საპარსი FSH-1245/4065544152826",
      "options": [],
      "original_price": null,
      "price": 11900,
      "purchasable_balance": null,
      "restrictions": [],
      "return_policy": null,
      "sell_by_weight_config": null,
      "should_display_purchasable_balance": false,
      "tags": [],
      "unit_info": null,
      "unit_price": null,
      "variant": null
    },
    {
      "id": "67af3b6e2e475465982e87a5",
      "advertising_info": null,
      "alcohol_permille": 0,
      "allowed_delivery_methods": [
        "homedelivery",
        "eatin",
        "takeaway"
      ],
      "available_times": [
        {
          "days": [
            1,
            2,
            3,
            4,
            5,
            6,
            7
          ],
          "start_time": 0,
          "end_time": 86400000
        }
      ],
      "barcode_gtin": "4714033526005",
      "caffeine_info": null,
      "can_be_promoted": {
        "basket": true,
        "venue": true,
        "credits": true
      },
      "checksum": "86bddaf483a0b8d52cf74e336976f5ac",
      "description": "",
      "deposit": null,
      "dietary_preferences": [],
      "disabled_info": null,
      "fulfillment_lead_time": null,
      "has_extra_info": false,
      "images": [
        {
          "url": "https://wolt-menu-images-cdn.wolt.com/menu-images/5eb50a8743ef4f7e46644db9/34ebf960-ead1-11ef-a375-dacba37cae33_211275.jpg",
          "blurhash": "j4:LHWGG;;GGKXy8lly8;;Cp4htT"
        }
      ],
      "is_cutlery": false,
      "is_no_contact_delivery_allowed": true,
      "is_wolt_plus_only": false,
      "lowest_price": null,
      "lowest_price_v2": null,
      "max_quantity_per_purchase": null,
      "min_quantity_per_purchase": null,
      "name": "DEFENDER მაუსი WRD OP მაუსი STORM GM-600L 1.5M/4714033526005",
      "options": [],
      "original_price": null,
      "price": 990,
      "purchasable_balance": null,
      "restrictions": [],
      "return_policy": null,
      "sell_by_weight_config": null,
      "should_display_purchasable_balance": false,
      "tags": [],
      "unit_info": null,
      "unit_price": null,
      "variant": null
    },
    {
      "id": "67af3b70d4b6e1dc4f9a1917",
      "advertising_info": null,
      "alcohol_permille": 0,
      "allowed_delivery_methods": [
        "homedelivery",
        "eatin",
        "takeaway"
      ],
      "available_times": [
        {
          "days": [
            1,
            2,
            3,
            4,
            5,
            6,
            7
          ],
          "start_time": 0,
          "end_time": 86400000
        }
      ],
      "barcode_gtin": "6948246600070",
      "caffeine_info": null,
      "can_be_promoted": {
        "basket": true,
        "venue": true,
        "credits": true
      },
      "checksum": "e3a7a04aae171d7c95e08e1f0f51bdce",
      "description": "",
      "deposit": null,
      "dietary_preferences": [],
      "disabled_info": null,
      "fulfillment_lead_time": null,
      "has_extra_info": false,
      "images": [
        {
          "url": "https://wolt-menu-images-cdn.wolt.com/menu-images/5eb50a8743ef4f7e46644db9/37bea3b8-ead1-11ef-98ce-d28e33cb4fe7_240519.jpg",
          "blurhash": "j7Z;DXpV;:KXlGCpKWtT;JGF4zlm"
        }
      ],
      "is_cutlery": false,
      "is_no_contact_delivery_allowed": true,
      "is_wolt_plus_only": false,
      "lowest_price": null,
      "lowest_price_v2": null,
      "max_quantity_per_purchase": null,
      "min_quantity_per_purchase": null,
      "name": "SOLLEX ჰუმიდიფაიერი SL 990/6948246600070",
      "options": [],
      "original_price": null,
      "price": 11900,
      "purchasable_balance": null,
      "restrictions": [],
      "return_policy": null,
      "sell_by_weight_config": null,
      "should_display_purchasable_balance": false,
      "tags": [],
      "unit_info": null,
      "unit_price": null,
      "variant": null
    },
    {
      "id": "67af3b7389cd8ed07ab6d1a2",
      "advertising_info": null,
      "alcohol_permille": 0,
      "allowed_delivery_methods": [
        "homedelivery",
        "eatin",
        "takeaway"
      ],
      "available_times": [
        {
          "days": [
            1,
            2,
            3,
            4,
            5,
            6,
            7
          ],
          "start_time": 0,
          "end_time": 86400000
        }
      ],
      "barcode_gtin": "4055555550803",
      "caffeine_info": null,
      "can_be_promoted": {
        "basket": true,
        "venue": true,
        "credits": true
      },
      "checksum": "2364ac6d719de35e8c0a49df4494eb14",
      "description": "",
      "deposit": null,
      "dietary_preferences": [],
      "disabled_info": null,
      "fulfillment_lead_time": null,
      "has_extra_info": false,
      "images": [
        {
          "url": "https://wolt-menu-images-cdn.wolt.com/menu-images/5eb50a8743ef4f7e46644db9/34f19780-ead1-11ef-979e-eab9f01fb128_165867.jpg",
          "blurhash": "j4:LHWGG;;KXGGGGGGpC;;tT4hGG"
        }
      ],
      "is_cutlery": false,
      "is_no_contact_delivery_allowed": true,
      "is_wolt_plus_only": false,
      "lowest_price": null,
      "lowest_price_v2": null,
      "max_quantity_per_purchase": null,
      "min_quantity_per_purchase": null,
      "name": "FRANKO ელექტრო ჩაიდანი 1.7ლ FKT1103 /4055555550803",
      "options": [],
      "original_price": null,
      "price": 8900,
      "purchasable_balance": null,
      "restrictions": [],
      "return_policy": null,
      "sell_by_weight_config": null,
      "should_display_purchasable_balance": false,
      "tags": [],
      "unit_info": null,
      "unit_price": null,
      "variant": null
    },
    {
      "id": "67af3b760681df437b75b1b1",
      "advertising_info": null,
      "alcohol_permille": 0,
      "allowed_delivery_methods": [
        "homedelivery",
        "eatin",
        "takeaway"
      ],
      "available_times": [
        {
          "days": [
            1,
            2,
            3,
            4,
            5,
            6,
            7
          ],
          "start_time": 0,
          "end_time": 86400000
        }
      ],
      "barcode_gtin": "740617326260",
      "caffeine_info": null,
      "can_be_promoted": {
        "basket": true,
        "venue": true,
        "credits": true
      },
      "checksum": "34b2582ab509144e69055d26c66c1f89",
      "description": "",
      "deposit": null,
      "dietary_preferences": [],
      "disabled_info": null,
      "fulfillment_lead_time": null,
      "has_extra_info": false,
      "images": [
        {
          "url": "https://wolt-menu-images-cdn.wolt.com/menu-images/5eb50a8743ef4f7e46644db9/4550e4c8-ead1-11ef-b094-6e8e3ff8100c_331162.jpg",
          "blurhash": "j4:LHWCG;;KXKXKXtTh4;;GF00lC"
        }
      ],
      "is_cutlery": false,
      "is_no_contact_delivery_allowed": true,
      "is_wolt_plus_only": false,
      "lowest_price": null,
      "lowest_price_v2": null,
      "max_quantity_per_purchase": null,
      "min_quantity_per_purchase": null,
      "name": "KINGSTON ფლეშკა DTXM/64GB/740617326260",
      "options": [],
      "original_price": null,
      "price": 2995,
      "purchasable_balance": null,
      "restrictions": [],
      "return_policy": null,
      "sell_by_weight_config": null,
      "should_display_purchasable_balance": false,
      "tags": [],
      "unit_info": null,
      "unit_price": null,
      "variant": null
    },
    {
      "id": "67af3b798328543d16037f21",
      "advertising_info": null,
      "alcohol_permille": 0,
      "allowed_delivery_methods": [
        "homedelivery",
        "eatin",
        "takeaway"
      ],
      "available_times": [
        {
          "days": [
            1,
            2,
            3,
            4,
            5,
            6,
            7
          ],
          "start_time": 0,
          "end_time": 86400000
        }
      ],
      "barcode_gtin": "6423808063543",
      "caffeine_info": null,
      "can_be_promoted": {
        "basket": true,
        "venue": true,
        "credits": true
      },
      "checksum": "5cb6dd032922cc71b10e5d55130286b7",
      "description": "",
      "deposit": null,
      "dietary_preferences": [],
      "disabled_info": {
        "disable_text": "Sold out",
        "disable_reason": null
      },
      "fulfillment_lead_time": null,
      "has_extra_info": false,
      "images": [
        {
          "url": "https://wolt-menu-images-cdn.wolt.com/menu-images/5eb50a8743ef4f7e46644db9/52ce0e6e-ead1-11ef-9525-56dca07ba816_354087.jpg",
          "blurhash": "j3:;LXKX;;llcPtTTtCq;;pC4hKX"
        }
      ],
      "is_cutlery": false,
      "is_no_contact_delivery_allowed": true,
      "is_wolt_plus_only": false,
      "lowest_price": null,
      "lowest_price_v2": null,
      "max_quantity_per_purchase": null,
      "min_quantity_per_purchase": null,
      "name": "HAUSBERG თმის საშრობი HB-26GR 1600W/6423808063543",
      "options": [],
      "original_price": null,
      "price": 2990,
      "purchasable_balance": 0,
      "restrictions": [],
      "return_policy": null,
      "sell_by_weight_config": null,
      "should_display_purchasable_balance": false,
      "tags": [],
      "unit_info": null,
      "unit_price": null,
      "variant": null
    },
    {
      "id": "67af3b7c44617e6cbfdf8b7d",
      "advertising_info": null,
      "alcohol_permille": 0,
      "allowed_delivery_methods": [
        "homedelivery",
        "eatin",
        "takeaway"
      ],
      "available_times": [
        {
          "days": [
            1,
            2,
            3,
            4,
            5,
            6,
            7
          ],
          "start_time": 0,
          "end_time": 86400000
        }
      ],
      "barcode_gtin": "8716309086219",
      "caffeine_info": null,
      "can_be_promoted": {
        "basket": true,
        "venue": true,
        "credits": true
      },
      "checksum": "0b5e2c45f17bb0ce7abd666fe5092088",
      "description": "",
      "deposit": null,
      "dietary_preferences": [],
      "disabled_info": null,
      "fulfillment_lead_time": null,
      "has_extra_info": false,
      "images": [
        {
          "url": "https://wolt-menu-images-cdn.wolt.com/menu-images/5eb50a8743ef4f7e46644db9/455512e6-ead1-11ef-95b7-3e3036117b3c_314512.jpg",
          "blurhash": "j8ZLrSyp;;KX8ytTXKGG;;GF4hpC"
        }
      ],
      "is_cutlery": false,
      "is_no_contact_delivery_allowed": true,
      "is_wolt_plus_only": false,
      "lowest_price": null,
      "lowest_price_v2": null,
      "max_quantity_per_purchase": null,
      "min_quantity_per_purchase": null,
      "name": "GEMBIRD MP-GAME-S მაუსის დასადები/8716309086219",
      "options": [],
      "original_price": null,
      "price": 990,
      "purchasable_balance": null,
      "restrictions": [],
      "return_policy": null,
      "sell_by_weight_config": null,
      "should_display_purchasable_balance": false,
      "tags": [],
      "unit_info": null,
      "unit_price": null,
      "variant": null
    },
    {
      "id": "67af3b7ff3f7826e594e6522",
      "advertising_info": null,
      "alcohol_permille": 0,
      "allowed_delivery_methods": [
        "homedelivery",
        "eatin",
        "takeaway"
      ],
      "available_times": [
        {
          "days": [
            1,
            2,
            3,
            4,
            5,
            6,
            7
          ],
          "start_time": 0,
          "end_time": 86400000
        }
      ],
      "barcode_gtin": "4065544152857",
      "caffeine_info": null,
      "can_be_promoted": {
        "basket": true,
        "venue": true,
        "credits": true
      },
      "checksum": "6382d6f1544f62396b36bff903cbe7f8",
      "description": "",
      "deposit": null,
      "dietary_preferences": [],
      "disabled_info": null,
      "fulfillment_lead_time": null,
      "has_extra_info": false,
      "images": [
        {
          "url": "https://wolt-menu-images-cdn.wolt.com/menu-images/5eb50a8743ef4f7e46644db9/5020a37a-ead1-11ef-8efb-d2432758f71d_351597.jpg",
          "blurhash": "j1;LX:KX;;KXPcy8llCp;;tT4hCp"
        }
      ],
      "is_cutlery": false,
      "is_no_contact_delivery_allowed": true,
      "is_wolt_plus_only": false,
      "lowest_price": null,
      "lowest_price_v2": null,
      "max_quantity_per_purchase": null,
      "min_quantity_per_purchase": null,
      "name": "FRANKO ტრიმერი FNT-9001/4065544152857",
      "options": [],
      "original_price": null,
      "price": 4990,
      "purchasable_balance": null,
      "restrictions": [],
      "return_policy": null,
      "sell_by_weight_config": null,
      "should_display_purchasable_balance": false,
      "tags": [],
      "unit_info": null,
      "unit_price": null,
      "variant": null
    }
  ],
  "options": [],
  "variant_groups": [],
  "metadata": {
    "next_page_token": "eyJsYXN0X251bSI6NDksInBhZ2UiOjJ9",
    "page": 1
  }
}