{
  "category": {
    "id": "6502d3a45bb9f84fa2a5ce55",
    "description": "",
    "images": [
      {
        "url": "https://wolt-menu-images-cdn.wolt.com/menu-images/5faa55d4f0e44faad51211cc/3260dac6-555e-11ee-ac32-566966d3a270_mie_so_i_ryby.jpg",
        "blurhash": "jdVtjmTd;;d3gQTtPbcOlFPtKXgO"
      }
    ],
    "name": "Mięso i ryby ",
    "slug": "mieso-i-ryby-131"
  },
  "categories": [],
  "items": [],
  "options": [],
  "variant_groups": [],
  "metadata": {
    "next_page_token": null,
    "page": 1
  }
}